Ch4/06.ScoreboardAndController/src/Controller.v
module Controller (
    input inc_i, dec_i, erase_i,
    input clk, rst,
    output reg inc_o, dec_o, erase_o
);
    localparam CLR = 0, CNT = 1;
    reg state, next_state;

    // 1. outputs
    // erase_o
    always @* begin
        erase_o = 0;

        case (state)
            CNT: if (erase_i && erasecnt == 4) erase_o = 1;
        endcase
    end

    // inc_o
    always @* begin
        inc_o = 0;

        case (state)
            CNT: if (inc_i && !dec_i) inc_o = 1;
        endcase
    end
    
    // dec_o
    always @* begin
        dec_o = 0;

        case (state)
            CNT: if (!inc_i && dec_i) dec_o = 1;
        endcase
    end

    // 2. FSM
    always @(posedge clk) begin
        state <= (rst)? CLR: next_state;
    end

    always @* begin
        case (state)
            CLR: next_state = (erase_i)? CLR : CNT;
            CNT: next_state = (erase_i && erasecnt == 4)? CLR : CNT;
        endcase
    end

    // 3. counter
    reg [3-1 : 0] erasecnt;

    // erasecnt
    always @(posedge clk) begin
        case (state)
            CNT: if (erase_i && erasecnt != 4) erasecnt <= erasecnt+1;
            CLR: erasecnt <= 0;
        endcase
    end
endmodule

Ch4/06.ScoreboardAndController/src/BCD2To7SegDecoder.v
module BCDTo7SegDecoder (
    input [4-1 : 0] bcd,
    output reg [7 : 1] seven
);

    always @(bcd) begin
        case (bcd)
            4'b0000 : seven = 7'b0111111;
            4'b0001 : seven = 7'b0000110;
            4'b0010 : seven = 7'b1011011;
            4'b0011 : seven = 7'b1001111;
            4'b0100 : seven = 7'b1100110;
            4'b0101 : seven = 7'b1101101;
            4'b0110 : seven = 7'b1111101;
            4'b0111 : seven = 7'b0000111;
            4'b1000 : seven = 7'b1111111;
            4'b1001 : seven = 7'b1101111;
            default : seven = 7'b0000000;
        endcase
    end
endmodule

Ch4/06.ScoreboardAndController/src/BCDCounter2Digit.v
module BCDCounter2Digit (
    input inc_i, dec_i, erase_i,
    input clk,
    output reg [4-1 : 0] tens_o, units_o
);
    // units_o
    always @* begin
        if (erase_i) begin
            units_o = 0;
        end else begin
            if (inc_i) units_o = (units == 9)? 0 : units + 1;
            if (dec_i) units_o = (units == 0)? 9 : units - 1;
        end
    end

    // tens_o
    always @* begin
        if (erase_i) begin
            tens_o = 0;
        end else begin
            if (inc_i && units == 9) tens_o = (tens == 9)? 0 : tens + 1;
            if (dec_i && units == 0) tens_o = (tens == 0)? 9 : tens - 1;
        end
    end

    reg [4-1 : 0] tens, units;

    // units
    always @(posedge clk) begin
        if (erase_i) begin
            units <= 0;
        end else begin
            if (inc_i) units <= (units == 9)? 0 : units + 1;
            if (dec_i) units <= (units == 0)? 9 : units - 1;
        end
    end

    // tens
    always @(posedge clk) begin
        if (erase_i) begin
            tens <= 0;
        end else begin
            if (inc_i && units == 9) tens <= (tens == 9)? 0 : tens + 1;
            if (dec_i && units == 0) tens <= (tens == 0)? 9 : tens - 1;
        end
    end
endmodule

Ch4/06.ScoreboardAndController/src/Scoreboard.v
module Scoreboard (
    input inc_i, dec_i, erase_i,
    input clk, rst,
    output [7 : 1] tens_7seg_o, units_7seg_o
);
    wire [4-1 : 0] tens, units;

    BCDCounter2Digit u1 (
        .inc_i(inc), .dec_i(dec), .erase_i(erase),
        .clk(clk),
        .tens_o(tens), .units_o(units)
    );

    BCDTo7SegDecoder u2 (
        .bcd(tens),
        .seven(tens_7seg_o)
    );

    BCDTo7SegDecoder u3 (
        .bcd(units),
        .seven(units_7seg_o)
    );

    wire inc, dec, erase;

    Controller u4 (
        .inc_i(inc_i), .dec_i(dec_i), .erase_i(erase_i),
        .clk(clk), .rst(rst),
        .inc_o(inc), .dec_o(dec), .erase_o(erase)
    );
endmodule

Ch4/06.ScoreboardAndController/test/Scoreboard_test.v
module t_Scoreboard;
    task delay (
        input [10:0] cycles
    );
        repeat (cycles) begin
            @(posedge clk);
        end
    endtask

    // erase the scoreboard
    task erase_scoreboard();
        begin
            delay(2);
            erase = 0;
            #2 erase = 1;
            delay(6);
            #2 erase = 0;
        end
    endtask

    reg inc, dec, erase;
    reg clk, rst;
    wire [7 : 1] tens_7seg, units_7seg;

    Scoreboard uut (
        .inc_i(inc), .dec_i(dec), .erase_i(erase),
        .clk(clk), .rst(rst),
        .tens_7seg_o(tens_7seg), .units_7seg_o(units_7seg)
    );

    initial begin
        $dumpfile("Scoreboard.vcd");
        $dumpvars;
    end

    initial begin
        clk = 0;
        forever #5 clk = ~clk;
    end

    initial begin
        // initialization
        inc = 0;
        dec = 0;
        erase = 0;

        // start the machine
        rst = 0;
        #2 rst = 1;
        @(posedge clk);
        #2 rst = 0;
        
        erase_scoreboard();

        // increment score
        delay(2);
        #2 inc = 1;
        @(posedge clk);
        #2 inc = 0;

        // decrement score
        delay(2);
        #2 dec = 1;
        @(posedge clk);
        #2 dec = 0;

        erase_scoreboard();

        // finish simulation
        delay(2);
        $finish;
    end
endmodule

Ch4/06.ScoreboardAndController/test/Scoreboard.vcd
$date
	Wed Nov  5 17:55:49 2025
$end
$version
	Icarus Verilog
$end
$timescale
	1s
$end
$scope module t_Scoreboard $end
$var wire 7 ! units_7seg [7:1] $end
$var wire 7 " tens_7seg [7:1] $end
$var reg 1 # clk $end
$var reg 1 $ dec $end
$var reg 1 % erase $end
$var reg 1 & inc $end
$var reg 1 ' rst $end
$scope module uut $end
$var wire 1 # clk $end
$var wire 1 $ dec_i $end
$var wire 1 % erase_i $end
$var wire 1 & inc_i $end
$var wire 1 ' rst $end
$var wire 7 ( units_7seg_o [7:1] $end
$var wire 4 ) units [3:0] $end
$var wire 7 * tens_7seg_o [7:1] $end
$var wire 4 + tens [3:0] $end
$var wire 1 , inc $end
$var wire 1 - erase $end
$var wire 1 . dec $end
$scope module u1 $end
$var wire 1 # clk $end
$var wire 1 , inc_i $end
$var wire 1 - erase_i $end
$var wire 1 . dec_i $end
$var reg 4 / tens [3:0] $end
$var reg 4 0 tens_o [3:0] $end
$var reg 4 1 units [3:0] $end
$var reg 4 2 units_o [3:0] $end
$upscope $end
$scope module u2 $end
$var wire 4 3 bcd [3:0] $end
$var reg 7 4 seven [7:1] $end
$upscope $end
$scope module u3 $end
$var wire 4 5 bcd [3:0] $end
$var reg 7 6 seven [7:1] $end
$upscope $end
$scope module u4 $end
$var wire 1 # clk $end
$var wire 1 $ dec_i $end
$var wire 1 % erase_i $end
$var wire 1 & inc_i $end
$var wire 1 ' rst $end
$var parameter 32 7 CLR $end
$var parameter 32 8 CNT $end
$var reg 1 . dec_o $end
$var reg 1 - erase_o $end
$var reg 3 9 erasecnt [2:0] $end
$var reg 1 , inc_o $end
$var reg 1 : next_state $end
$var reg 1 ; state $end
$upscope $end
$upscope $end
$scope task delay $end
$var reg 11 < cycles [10:0] $end
$upscope $end
$scope task erase_scoreboard $end
$upscope $end
$upscope $end
$enddefinitions $end
$comment Show the parameter values. $end
$dumpall
b1 8
b0 7
$end
#0
$dumpvars
bx <
x;
x:
bx 9
bx 6
bx 5
bx 4
bx 3
bx 2
bx 1
bx 0
bx /
0.
0-
0,
bx +
bx *
bx )
bx (
0'
0&
0%
0$
0#
bx "
bx !
$end
#2
1'
#5
1:
0;
1#
#7
b10 <
0'
#10
0#
#15
b0 9
1;
1#
#20
0#
#25
1#
#27
b110 <
1%
#30
0#
#35
b1 9
1#
#40
0#
#45
b10 9
1#
#50
0#
#55
b11 9
1#
#60
0#
#65
b111111 "
b111111 *
b111111 4
b111111 !
b111111 (
b111111 6
b0 +
b0 0
b0 3
b0 )
b0 2
b0 5
1-
0:
b100 9
1#
#70
0#
#75
0-
0;
b0 /
b0 1
1#
#80
0#
#85
b0 9
1#
#87
1:
b10 <
0%
#90
0#
#95
1;
1#
#100
0#
#105
1#
#107
b110 !
b110 (
b110 6
b1 )
b1 2
b1 5
1,
1&
#110
0#
#115
b1011011 !
b1011011 (
b1011011 6
b10 )
b10 2
b10 5
b1 1
1#
#117
0,
0&
#120
0#
#125
1#
#130
0#
#135
1#
#137
b111111 !
b111111 (
b111111 6
b0 )
b0 2
b0 5
1.
1$
#140
0#
#145
b1101111 "
b1101111 *
b1101111 4
b1101111 !
b1101111 (
b1101111 6
b1001 +
b1001 0
b1001 3
b1001 )
b1001 2
b1001 5
b0 1
1#
#147
0.
0$
#150
0#
#155
1#
#160
0#
#165
1#
#167
b110 <
1%
#170
0#
#175
b1 9
1#
#180
0#
#185
b10 9
1#
#190
0#
#195
b11 9
1#
#200
0#
#205
b111111 "
b111111 *
b111111 4
b111111 !
b111111 (
b111111 6
b0 +
b0 0
b0 3
b0 )
b0 2
b0 5
0:
1-
b100 9
1#
#210
0#
#215
0-
0;
1#
#220
0#
#225
b0 9
1#
#227
1:
b10 <
0%
#230
0#
#235
1;
1#
