Ch4/09.ArrayMultiplier/ArrayMultiplier.srcs/sources_1/new/HalfAdder.v
module HalfAdder (
    input a, b,
    output cout, sum
);
    assign {cout, sum} = a + b;
endmodule

Ch4/09.ArrayMultiplier/ArrayMultiplier.srcs/sources_1/new/FullAdder.v
`timescale 1ns / 1ps
//////////////////////////////////////////////////////////////////////////////////
// Company: 
// Engineer: 
// 
// Create Date: 11/20/2025 07:51:52 AM
// Design Name: 
// Module Name: FullAdder
// Project Name: 
// Target Devices: 
// Tool Versions: 
// Description: 
// 
// Dependencies: 
// 
// Revision:
// Revision 0.01 - File Created
// Additional Comments:
// 
//////////////////////////////////////////////////////////////////////////////////


module FullAdder (
    input a, b, cin,
    output cout, sum
);
    assign {cout, sum} = a + b + cin;
endmodule

Ch4/09.ArrayMultiplier/ArrayMultiplier.srcs/sources_1/new/ArrayMultiplier.v
module ArrayMultiplier (
    input [4-1 : 0] X_i, Y_i,
    output [8-1 : 0] P_o
);
    reg [4-1 : 0] XY [4-1 : 0];
    wire [4-1 : 0] S1, S2, S3;
    wire [4-1 : 0] C1, C2, C3;

    // XY
    integer i, j;
    always @* begin
        for (i = 0; i < 4; i=i+1) begin
            for (j = 0; j < 4; j=j+1) begin
                XY[i][j] = X_i[j] & Y_i[i];
            end
        end
    end

    // full adders and half adders
    FullAdder FA1 (XY[0][2], XY[1][1], C1[0], C1[1], S1[1]);
    FullAdder FA2 (XY[0][3], XY[1][2], C1[1], C1[2], S1[2]);
    FullAdder FA3 (S1[2], XY[2][1], C2[0], C2[1], S2[1]);
    FullAdder FA4 (S1[3], XY[2][2], C2[1], C2[2], S2[2]);
    FullAdder FA5 (C1[3], XY[2][3], C2[2], C2[3], S2[3]);
    FullAdder FA6 (S2[2], XY[3][1], C3[0], C3[1], S3[1]);
    FullAdder FA7 (S2[3], XY[3][2], C3[1], C3[2], S3[2]);
    FullAdder FA8 (C2[3], XY[3][3], C3[2], C3[3], S3[3]);

    HalfAdder HA1 (XY[0][1], XY[1][0], C1[0], S1[0]);
    HalfAdder HA2 (XY[1][3], C1[2], C1[3], S1[3]);
    HalfAdder HA3 (S1[1], XY[2][0], C2[0], S2[0]);
    HalfAdder HA4 (S2[1], XY[3][0], C3[0], S3[0]);

    // P_o
    assign P_o[0] = XY[0][0];
    assign P_o[1] = S1[0];
    assign P_o[2] = S2[0];
    assign P_o[3] = S3[0];
    assign P_o[4] = S3[1];
    assign P_o[5] = S3[2];
    assign P_o[6] = S3[3];
    assign P_o[7] = C3[3];
endmodule

Ch4/09.ArrayMultiplier/ArrayMultiplier.srcs/sim_1/new/ArrayMultiplier_tb.v
`timescale 1ns / 1ps
//////////////////////////////////////////////////////////////////////////////////
// Company: 
// Engineer: 
// 
// Create Date: 11/20/2025 07:59:17 AM
// Design Name: 
// Module Name: ArrayMultiplier_tb
// Project Name: 
// Target Devices: 
// Tool Versions: 
// Description: 
// 
// Dependencies: 
// 
// Revision:
// Revision 0.01 - File Created
// Additional Comments:
// 
//////////////////////////////////////////////////////////////////////////////////


module ArrayMultiplier_tb;
    reg [4-1 : 0] X_i, Y_i;
    wire [8-1 : 0] P_o;

    ArrayMultiplier uut (
        .X_i(X_i), .Y_i(Y_i),
        .P_o(P_o)
    );

    initial begin
        $dumpfile("ArrayMultiplier.vcd");
        $dumpvars;
    end

    reg [4-1 : 0] i, j;
    initial begin
        for (i = 0; i < 5; i=i+1) begin
            for (j = 0; j < 5; j=j+1) begin
                X_i = i;
                Y_i = j;

                #10
                if (P_o !== i*j) begin
                    $display("Wrong Answer! %d (%b) x %d (%b) != %d (%b)", i, i, j, j, P_o, P_o);
                    #10 $finish;
                end
            end
        end

        $display("All test cases passed!");
        #10 $finish;
    end
endmodule

Ch4/09.ArrayMultiplier/ArrayMultiplier.sim/sim_1/behav/xsim/ArrayMultiplier.vcd
$date
   Thu Nov 20 08:00:44 2025
$end

$version
  2025.1.1
  $dumpfile ("ArrayMultiplier.vcd") 
$end

$timescale
  1ps
$end

$scope module ArrayMultiplier_tb $end
$var reg 4 ! X_i [3:0] $end
$var reg 4 " Y_i [3:0] $end
$var wire 8 # P_o [7:0] $end
$var reg 4 $ i [3:0] $end
$var reg 4 % j [3:0] $end
$scope module uut $end
$var wire 4 & X_i [3:0] $end
$var wire 4 ' Y_i [3:0] $end
$var wire 8 # P_o [7:0] $end
$var wire 4 ( S1 [3:0] $end
$var wire 4 ) S2 [3:0] $end
$var wire 4 * S3 [3:0] $end
$var wire 4 + C1 [3:0] $end
$var wire 4 , C2 [3:0] $end
$var wire 4 - C3 [3:0] $end
$var integer 32 . i [31:0] $end
$var integer 32 / j [31:0] $end
$scope module FA1 $end
$var wire 1 0 a $end
$var wire 1 1 b $end
$var wire 1 2 cin $end
$var wire 1 3 cout $end
$var wire 1 4 sum $end
$upscope $end
$scope module FA2 $end
$var wire 1 5 a $end
$var wire 1 6 b $end
$var wire 1 3 cin $end
$var wire 1 7 cout $end
$var wire 1 8 sum $end
$upscope $end
$scope module FA3 $end
$var wire 1 8 a $end
$var wire 1 9 b $end
$var wire 1 : cin $end
$var wire 1 ; cout $end
$var wire 1 < sum $end
$upscope $end
$scope module FA4 $end
$var wire 1 = a $end
$var wire 1 > b $end
$var wire 1 ; cin $end
$var wire 1 ? cout $end
$var wire 1 @ sum $end
$upscope $end
$scope module FA5 $end
$var wire 1 A a $end
$var wire 1 B b $end
$var wire 1 ? cin $end
$var wire 1 C cout $end
$var wire 1 D sum $end
$upscope $end
$scope module FA6 $end
$var wire 1 @ a $end
$var wire 1 E b $end
$var wire 1 F cin $end
$var wire 1 G cout $end
$var wire 1 H sum $end
$upscope $end
$scope module FA7 $end
$var wire 1 D a $end
$var wire 1 I b $end
$var wire 1 G cin $end
$var wire 1 J cout $end
$var wire 1 K sum $end
$upscope $end
$scope module FA8 $end
$var wire 1 C a $end
$var wire 1 L b $end
$var wire 1 J cin $end
$var wire 1 M cout $end
$var wire 1 N sum $end
$upscope $end
$scope module HA1 $end
$var wire 1 O a $end
$var wire 1 P b $end
$var wire 1 2 cout $end
$var wire 1 Q sum $end
$upscope $end
$scope module HA2 $end
$var wire 1 R a $end
$var wire 1 7 b $end
$var wire 1 A cout $end
$var wire 1 = sum $end
$upscope $end
$scope module HA3 $end
$var wire 1 4 a $end
$var wire 1 S b $end
$var wire 1 : cout $end
$var wire 1 T sum $end
$upscope $end
$scope module HA4 $end
$var wire 1 < a $end
$var wire 1 U b $end
$var wire 1 F cout $end
$var wire 1 V sum $end
$upscope $end
$upscope $end
$upscope $end
$enddefinitions $end

#0
$dumpvars
b0 !
b0 "
b0 #
b0 $
b0 %
b0 &
b0 '
b0 (
b0 )
b0 *
b0 +
b0 ,
b0 -
b100 .
b100 /
00
01
02
03
04
05
06
07
08
09
0:
0;
0<
0=
0>
0?
0@
0A
0B
0C
0D
0E
0F
0G
0H
0I
0J
0K
0L
0M
0N
0O
0P
0Q
0R
0S
0T
0U
0V
$end

#10000
b1 "
b1 %
b1 '
b100 .
b100 /

#20000
b10 "
b10 %
b10 '
b100 .
b100 /

#30000
b11 "
b11 %
b11 '
b100 .
b100 /

#40000
b100 "
b100 %
b100 '
b100 .
b100 /

#50000
b1 !
b0 "
b1 $
b0 %
b1 &
b0 '
b100 .
b100 /

#60000
b1 "
b1 #
b1 %
b1 '
b100 .
b100 /

#70000
b10 "
b10 #
b10 %
b10 '
b1 (
b100 .
b100 /
1P
1Q

#80000
b11 "
b11 #
b11 %
b11 '
b100 .
b100 /

#90000
b100 "
b100 #
b100 %
b100 '
b0 (
b1 )
b100 .
b100 /
0P
0Q
1S
1T

#100000
b10 !
b0 "
b0 #
b10 $
b0 %
b10 &
b0 '
b0 )
b100 .
b100 /
0S
0T

#110000
b1 "
b10 #
b1 %
b1 '
b1 (
b100 .
b100 /
1O
1Q

#120000
b10 "
b100 #
b10 %
b10 '
b10 (
b1 )
b100 .
b100 /
11
14
0O
0Q
1T

#130000
b11 "
b110 #
b11 %
b11 '
b11 (
b100 .
b100 /
1O
1Q

#140000
b100 "
b1000 #
b100 %
b100 '
b0 (
b10 )
b1 *
b100 .
b100 /
01
04
19
1<
0O
0Q
0T
1V

#150000
b11 !
b0 "
b0 #
b11 $
b0 %
b11 &
b0 '
b0 )
b0 *
b100 .
b100 /
09
0<
0V

#160000
b1 "
b11 #
b1 %
b1 '
b1 (
b100 .
b100 /
1O
1Q

#170000
b10 "
b110 #
b10 %
b10 '
b11 (
b1 )
b100 .
b100 /
11
14
0O
1P
1T

#180000
b11 "
b1001 #
b11 %
b11 '
b100 (
b10 )
b1 *
b11 +
b100 .
b100 /
12
13
04
18
1<
1O
0Q
0T
1V

#190000
b100 "
b1100 #
b100 %
b100 '
b0 (
b11 )
b1 *
b0 +
b0 ,
b100 .
b100 /
01
02
03
04
08
19
0:
0;
1<
0@
0H
0O
0P
1S
1T
1V

#200000
b100 !
b0 "
b0 #
b100 $
b0 %
b100 &
b0 '
b0 )
b0 *
b100 .
b100 /
09
0<
0S
0T
0V

#210000
b1 "
b100 #
b1 %
b1 '
b10 (
b1 )
b100 .
b100 /
10
14
1T

#220000
b10 "
b1000 #
b10 %
b10 '
b100 (
b10 )
b1 *
b100 .
b100 /
00
04
16
18
1<
0T
1V

#230000
b11 "
b1100 #
b11 %
b11 '
b110 (
b11 )
b100 .
b100 /
10
14
1T

#240000
b100 "
b10000 #
b100 %
b100 '
b0 (
b100 )
b10 *
b100 .
b100 /
00
04
06
08
0<
1>
1@
1H
0T
0V

#250000
b101 $
b101 %
