Ch4/07.SynchronizationAndDebouncing/src/SinglePulser.v
module SinglePulser (
    input syncpress_i,
    input clk, rst,
    output reg SP_o
);
    localparam S0 = 0, S1 = 1;
    reg state, next_state;

    // state
    always @(posedge clk) begin
        state <= (rst)? S0 : next_state;
    end

    always @* begin
        case (state)
            S0: next_state = (syncpress_i)? S1 : S0;
            S1: next_state = (syncpress_i)? S1 : S0;
        endcase
    end

    // SP_o
    always @* begin
        case (state)
            S0: SP_o = (syncpress_i)? 1 : 0;
            S1: SP_o = 0;
        endcase
    end
endmodule

Ch4/07.SynchronizationAndDebouncing/test/SinglePulser_test.v
module t_SinglePulser;
    reg syncpress;
    reg clk, rst;
    wire SP;

    SinglePulser uut (
        .syncpress_i(syncpress),
        .clk(clk), .rst(rst),
        .SP_o(SP)
    );

    initial begin
        $dumpfile("SinglePulser.vcd");
        $dumpvars;
    end

    initial begin
        clk = 0;
        forever #5 clk = ~clk;
    end

    initial begin
        rst = 0;
        #2 rst = 1;
        @(posedge clk);
        #2 rst = 0;

        syncpress = 0;
        @(posedge clk)
        syncpress = 1;
        repeat(3) @(posedge clk);

        syncpress = 0;
        @(posedge clk)
        syncpress = 1;
        repeat(4) @(posedge clk);

        syncpress = 0;
        #10 $finish;
    end
endmodule

Ch4/07.SynchronizationAndDebouncing/test/SinglePulser.vcd
$date
	Wed Nov  5 16:53:23 2025
$end
$version
	Icarus Verilog
$end
$timescale
	1s
$end
$scope module t_SinglePulser $end
$var wire 1 ! SP $end
$var reg 1 " clk $end
$var reg 1 # rst $end
$var reg 1 $ syncpress $end
$scope module uut $end
$var wire 1 " clk $end
$var wire 1 # rst $end
$var wire 1 $ syncpress_i $end
$var parameter 32 % S0 $end
$var parameter 32 & S1 $end
$var reg 1 ! SP_o $end
$var reg 1 ' next_state $end
$var reg 1 ( state $end
$upscope $end
$upscope $end
$enddefinitions $end
$comment Show the parameter values. $end
$dumpall
b1 &
b0 %
$end
#0
$dumpvars
x(
x'
x$
0#
0"
x!
$end
#2
1#
#5
0(
1"
#7
0'
0!
0$
0#
#10
0"
#15
1!
1'
1$
1"
#20
0"
#25
0!
1(
1"
#30
0"
#35
1"
#40
0"
#45
0'
0$
1"
#50
0"
#55
1!
0(
1'
1$
1"
#60
0"
#65
0!
1(
1"
#70
0"
#75
1"
#80
0"
#85
1"
#90
0"
#95
0'
0$
1"
#100
0"
#105
0(
1"
