Ch4/02.BCDAdder/src/CarryBCDController.v
module CarryBCDController (
    input [5-1 : 0] sum,
    output [4-1 : 0] bcd,
    output carry
);
    assign carry = (sum > 9)? 1 : 0;
    // A ~ F are not meaningful in BCD
    assign bcd = (sum > 9)? sum+6 : sum;
endmodule

NYCU/DigitalSystemsDesign/Ch4/02.BCDAdder/src/FullAdder.v
module FullAdder (
    input [4-1 : 0] a, b,
    input cin,
    output [5-1 : 0] s
);
    assign s = a + b + cin;
endmodule

NYCU/DigitalSystemsDesign/Ch4/02.BCDAdder/src/BCDAdder.v
module BCDAdder (
    input [8-1 : 0] a, b,
    output [9-1 : 0] ans
);

    wire lower_carry, upper_carry;

    wire [5-1 : 0] s0, s1;

    wire [4-1 : 0] lower_ans, upper_ans;
    
    FullAdder lower_adder (
        .a(a[3:0]), .b(b[3:0]),
        .cin(1'b0), .s(s0)
    );

    FullAdder upper_adder (
        .a(a[7:4]), .b(b[7:4]),
        .cin(lower_carry), .s(s1)
    );

    CarryBCDController lower_controller (
        .sum(s0),
        .bcd(lower_ans),
        .carry(lower_carry)
    );

    CarryBCDController upper_controller (
        .sum(s1),
        .bcd(upper_ans),
        .carry(upper_carry)
    );

    assign ans = {upper_carry, upper_ans, lower_ans};
endmodule

Ch4/02.BCDAdder/test/BCDAdder_test.v
`timescale 1ns/1ps
module t_BCDAdder;
    reg [8-1 : 0] a, b;
    wire [9-1 : 0] ans;

    BCDAdder uut (
        .a(a), .b(b),
        .ans(ans)
    );

    initial begin
        $dumpfile("BCDAdder.vcd");
        $dumpvars;
    end

    // file handles
    integer fa, fb, fc;

    // correct sum
    reg [9-1 : 0] golden;            if (ans !== golden) begin
                $display("a=%d, b=%d, ans=%d, golden=%d", a, b, ans, golden);
                #20 $finish;
            end

    integer status;


    initial begin
        fa = $fopen("../test_cases/a.txt", "r");
        fb = $fopen("../test_cases/b.txt", "r");
        fc = $fopen("../test_cases/c.txt", "r");

        while (!$feof(fa)) begin
            #10
            status = $fscanf(fa, "%b\n", a);
            status = $fscanf(fb, "%b\n", b);
            status = $fscanf(fc, "%b\n", golden);

            #10

            // $display("a=%b, b=%b, ans=%b, golden=%b", a, b, ans, golden);

            if (ans !== golden) begin
                $display("a=%d, b=%d, ans=%d, golden=%d", a, b, ans, golden);
                #20 $finish;
            end
        end

        $display("All test cases passed!");

        $fclose(fa);
        $fclose(fb);
        $fclose(fc);

        $finish;
    end
endmodule

NYCU/DigitalSystemsDesign/Ch4/02.BCDAdder/test/BCDAdder.vcd
$date
	Mon Oct 27 12:04:37 2025
$end
$version
	Icarus Verilog
$end
$timescale
	1s
$end
$scope module t_BCDAdder $end
$var wire 9 ! ans [8:0] $end
$var reg 8 " a [7:0] $end
$var reg 8 # b [7:0] $end
$var reg 9 $ golden [8:0] $end
$var integer 32 % fa [31:0] $end
$var integer 32 & fb [31:0] $end
$var integer 32 ' fc [31:0] $end
$var integer 32 ( status [31:0] $end
$scope module uut $end
$var wire 8 ) a [7:0] $end
$var wire 8 * b [7:0] $end
$var wire 1 + upper_carry $end
$var wire 4 , upper_ans [3:0] $end
$var wire 5 - s1 [4:0] $end
$var wire 5 . s0 [4:0] $end
$var wire 1 / lower_carry $end
$var wire 4 0 lower_ans [3:0] $end
$var wire 9 1 ans [8:0] $end
$scope module lower_adder $end
$var wire 4 2 a [3:0] $end
$var wire 4 3 b [3:0] $end
$var wire 1 4 cin $end
$var wire 5 5 s [4:0] $end
$upscope $end
$scope module lower_controller $end
$var wire 5 6 sum [4:0] $end
$var wire 1 / carry $end
$var wire 4 7 bcd [3:0] $end
$upscope $end
$scope module upper_adder $end
$var wire 4 8 a [3:0] $end
$var wire 4 9 b [3:0] $end
$var wire 1 / cin $end
$var wire 5 : s [4:0] $end
$upscope $end
$scope module upper_controller $end
$var wire 5 ; sum [4:0] $end
$var wire 1 + carry $end
$var wire 4 < bcd [3:0] $end
$upscope $end
$upscope $end
$upscope $end
$enddefinitions $end
$comment Show the parameter values. $end
$dumpall
$end
#0
$dumpvars
bx <
bx ;
bx :
bx 9
bx 8
bx 7
bx 6
bx 5
04
bx 3
bx 2
bx 1
bx 0
x/
bx .
bx -
bx ,
x+
bx *
bx )
bx (
b10000000000000000000000000000101 '
b10000000000000000000000000000100 &
b10000000000000000000000000000011 %
bx $
bx #
bx "
bx !
$end
#10
0+
b0 ,
b0 <
b0 -
b0 :
b0 ;
0/
b0 !
b0 1
b0 0
b0 7
b0 .
b0 5
b0 6
b0 3
b0 9
b0 2
b0 8
b0 $
b0 #
b0 *
b1 (
b0 "
b0 )
#30
b1 !
b1 1
b1 0
b1 7
b1 .
b1 5
b1 6
b1 3
b1 $
b1 #
b1 *
#50
b10 !
b10 1
b10 0
b10 7
b10 .
b10 5
b10 6
b10 3
b10 $
b10 #
b10 *
#70
b11 !
b11 1
b11 0
b11 7
b11 .
b11 5
b11 6
b11 3
b11 $
b11 #
b11 *
#90
b100 !
b100 1
b100 0
b100 7
b100 .
b100 5
b100 6
b100 3
b100 $
b100 #
b100 *
#110
b101 !
b101 1
b101 0
b101 7
b101 .
b101 5
b101 6
b101 3
b101 $
b101 #
b101 *
#130
b110 !
b110 1
b110 0
b110 7
b110 .
b110 5
b110 6
b110 3
b110 $
b110 #
b110 *
#150
b111 !
b111 1
b111 0
b111 7
b111 .
b111 5
b111 6
b111 3
b111 $
b111 #
b111 *
#170
b1000 !
b1000 1
b1000 0
b1000 7
b1000 .
b1000 5
b1000 6
b1000 3
b1000 $
b1000 #
b1000 *
#190
b1001 !
b1001 1
b1001 0
b1001 7
b1001 .
b1001 5
b1001 6
b1001 3
b1001 $
b1001 #
b1001 *
#210
b0 0
b0 7
b10000 !
b10000 1
b1 ,
b1 <
b0 .
b0 5
b0 6
b0 3
b1 -
b1 :
b1 ;
b1 9
b10000 $
b10000 #
b10000 *
#230
b10001 !
b10001 1
b1 0
b1 7
b1 .
b1 5
b1 6
b1 3
b10001 $
b10001 #
b10001 *
#250
b10010 !
b10010 1
b10 0
b10 7
b10 .
b10 5
b10 6
b10 3
b10010 $
b10010 #
b10010 *
#270
b10011 !
b10011 1
b11 0
b11 7
b11 .
b11 5
b11 6
b11 3
b10011 $
b10011 #
b10011 *
#290
b10100 !
b10100 1
b100 0
b100 7
b100 .
b100 5
b100 6
b100 3
b10100 $
b10100 #
b10100 *
#310
b10101 !
b10101 1
b101 0
b101 7
b101 .
b101 5
b101 6
b101 3
b10101 $
b10101 #
b10101 *
#330
b10110 !
b10110 1
b110 0
b110 7
b110 .
b110 5
b110 6
b110 3
b10110 $
b10110 #
b10110 *
#350
b10111 !
b10111 1
b111 0
b111 7
b111 .
b111 5
b111 6
b111 3
b10111 $
b10111 #
b10111 *
#370
b11000 !
b11000 1
b1000 0
b1000 7
b1000 .
b1000 5
b1000 6
b1000 3
b11000 $
b11000 #
b11000 *
#390
b11001 !
b11001 1
b1001 0
b1001 7
b1001 .
b1001 5
b1001 6
b1001 3
b11001 $
b11001 #
b11001 *
#410
b0 0
b0 7
b100000 !
b100000 1
b10 ,
b10 <
b0 .
b0 5
b0 6
b0 3
b10 -
b10 :
b10 ;
b10 9
b100000 $
b100000 #
b100000 *
#430
b100001 !
b100001 1
b1 0
b1 7
b1 .
b1 5
b1 6
b1 3
b100001 $
b100001 #
b100001 *
#450
b100010 !
b100010 1
b10 0
b10 7
b10 .
b10 5
b10 6
b10 3
b100010 $
b100010 #
b100010 *
#470
b100011 !
b100011 1
b11 0
b11 7
b11 .
b11 5
b11 6
b11 3
b100011 $
b100011 #
b100011 *
#490
b100100 !
b100100 1
b100 0
b100 7
b100 .
b100 5
b100 6
b100 3
b100100 $
b100100 #
b100100 *
#510
b100101 !
b100101 1
b101 0
b101 7
b101 .
b101 5
b101 6
b101 3
b100101 $
b100101 #
b100101 *
#530
b100110 !
b100110 1
b110 0
b110 7
b110 .
b110 5
b110 6
b110 3
b100110 $
b100110 #
b100110 *
#550
b100111 !
b100111 1
b111 0
b111 7
b111 .
b111 5
b111 6
b111 3
b100111 $
b100111 #
b100111 *
#570
b101000 !
b101000 1
b1000 0
b1000 7
b1000 .
b1000 5
b1000 6
b1000 3
b101000 $
b101000 #
b101000 *
#590
b101001 !
b101001 1
b1001 0
b1001 7
b1001 .
b1001 5
b1001 6
b1001 3
b101001 $
b101001 #
b101001 *
#610
b0 0
b0 7
b110000 !
b110000 1
b11 ,
b11 <
b0 .
b0 5
b0 6
b0 3
b11 -
b11 :
b11 ;
b11 9
b110000 $
b110000 #
b110000 *
#630
b110001 !
b110001 1
b1 0
b1 7
b1 .
b1 5
b1 6
b1 3
b110001 $
b110001 #
b110001 *
#650
b110010 !
b110010 1
b10 0
b10 7
b10 .
b10 5
b10 6
b10 3
b110010 $
b110010 #
b110010 *
#670
b110011 !
b110011 1
b11 0
b11 7
b11 .
b11 5
b11 6
b11 3
b110011 $
b110011 #
b110011 *
#690
b110100 !
b110100 1
b100 0
b100 7
b100 .
b100 5
b100 6
b100 3
b110100 $
b110100 #
b110100 *
#710
b110101 !
b110101 1
b101 0
b101 7
b101 .
b101 5
b101 6
b101 3
b110101 $
b110101 #
b110101 *
#730
b110110 !
b110110 1
b110 0
b110 7
b110 .
b110 5
b110 6
b110 3
b110110 $
b110110 #
b110110 *
#750
b110111 !
b110111 1
b111 0
b111 7
b111 .
b111 5
b111 6
b111 3
b110111 $
b110111 #
b110111 *
#770
b111000 !
b111000 1
b1000 0
b1000 7
b1000 .
b1000 5
b1000 6
b1000 3
b111000 $
b111000 #
b111000 *
#790
b111001 !
b111001 1
b1001 0
b1001 7
b1001 .
b1001 5
b1001 6
b1001 3
b111001 $
b111001 #
b111001 *
#810
b0 0
b0 7
b1000000 !
b1000000 1
b100 ,
b100 <
b0 .
b0 5
b0 6
b0 3
b100 -
b100 :
b100 ;
b100 9
b1000000 $
b1000000 #
b1000000 *
#830
b1000001 !
b1000001 1
b1 0
b1 7
b1 .
b1 5
b1 6
b1 3
b1000001 $
b1000001 #
b1000001 *
#850
b1000010 !
b1000010 1
b10 0
b10 7
b10 .
b10 5
b10 6
b10 3
b1000010 $
b1000010 #
b1000010 *
#870
b1000011 !
b1000011 1
b11 0
b11 7
b11 .
b11 5
b11 6
b11 3
b1000011 $
b1000011 #
b1000011 *
#890
b1000100 !
b1000100 1
b100 0
b100 7
b100 .
b100 5
b100 6
b100 3
b1000100 $
b1000100 #
b1000100 *
#910
b1000101 !
b1000101 1
b101 0
b101 7
b101 .
b101 5
b101 6
b101 3
b1000101 $
b1000101 #
b1000101 *
#930
b1000110 !
b1000110 1
b110 0
b110 7
b110 .
b110 5
b110 6
b110 3
b1000110 $
b1000110 #
b1000110 *
#950
b1000111 !
b1000111 1
b111 0
b111 7
b111 .
b111 5
b111 6
b111 3
b1000111 $
b1000111 #
b1000111 *
#970
b1001000 !
b1001000 1
b1000 0
b1000 7
b1000 .
b1000 5
b1000 6
b1000 3
b1001000 $
b1001000 #
b1001000 *
#990
b1001001 !
b1001001 1
b1001 0
b1001 7
b1001 .
b1001 5
b1001 6
b1001 3
b1001001 $
b1001001 #
b1001001 *
#1010
b0 0
b0 7
b1010000 !
b1010000 1
b101 ,
b101 <
b0 .
b0 5
b0 6
b0 3
b101 -
b101 :
b101 ;
b101 9
b1010000 $
b1010000 #
b1010000 *
#1030
b1010001 !
b1010001 1
b1 0
b1 7
b1 .
b1 5
b1 6
b1 3
b1010001 $
b1010001 #
b1010001 *
#1050
b1010010 !
b1010010 1
b10 0
b10 7
b10 .
b10 5
b10 6
b10 3
b1010010 $
b1010010 #
b1010010 *
#1070
b1010011 !
b1010011 1
b11 0
b11 7
b11 .
b11 5
b11 6
b11 3
b1010011 $
b1010011 #
b1010011 *
#1090
b1010100 !
b1010100 1
b100 0
b100 7
b100 .
b100 5
b100 6
b100 3
b1010100 $
b1010100 #
b1010100 *
#1110
b1010101 !
b1010101 1
b101 0
b101 7
b101 .
b101 5
b101 6
b101 3
b1010101 $
b1010101 #
b1010101 *
#1130
b1010110 !
b1010110 1
b110 0
b110 7
b110 .
b110 5
b110 6
b110 3
b1010110 $
b1010110 #
b1010110 *
#1150
b1010111 !
b1010111 1
b111 0
b111 7
b111 .
b111 5
b111 6
b111 3
b1010111 $
b1010111 #
b1010111 *
#1170
b1011000 !
b1011000 1
b1000 0
b1000 7
b1000 .
b1000 5
b1000 6
b1000 3
b1011000 $
b1011000 #
b1011000 *
#1190
b1011001 !
b1011001 1
b1001 0
b1001 7
b1001 .
b1001 5
b1001 6
b1001 3
b1011001 $
b1011001 #
b1011001 *
#1210
b0 0
b0 7
b1100000 !
b1100000 1
b110 ,
b110 <
b0 .
b0 5
b0 6
b0 3
b110 -
b110 :
b110 ;
b110 9
b1100000 $
b1100000 #
b1100000 *
#1230
b1100001 !
b1100001 1
b1 0
b1 7
b1 .
b1 5
b1 6
b1 3
b1100001 $
b1100001 #
b1100001 *
#1250
b1100010 !
b1100010 1
b10 0
b10 7
b10 .
b10 5
b10 6
b10 3
b1100010 $
b1100010 #
b1100010 *
#1270
b1100011 !
b1100011 1
b11 0
b11 7
b11 .
b11 5
b11 6
b11 3
b1100011 $
b1100011 #
b1100011 *
#1290
b1100100 !
b1100100 1
b100 0
b100 7
b100 .
b100 5
b100 6
b100 3
b1100100 $
b1100100 #
b1100100 *
#1310
b1100101 !
b1100101 1
b101 0
b101 7
b101 .
b101 5
b101 6
b101 3
b1100101 $
b1100101 #
b1100101 *
#1330
b1100110 !
b1100110 1
b110 0
b110 7
b110 .
b110 5
b110 6
b110 3
b1100110 $
b1100110 #
b1100110 *
#1350
b1100111 !
b1100111 1
b111 0
b111 7
b111 .
b111 5
b111 6
b111 3
b1100111 $
b1100111 #
b1100111 *
#1370
b1101000 !
b1101000 1
b1000 0
b1000 7
b1000 .
b1000 5
b1000 6
b1000 3
b1101000 $
b1101000 #
b1101000 *
#1390
b1101001 !
b1101001 1
b1001 0
b1001 7
b1001 .
b1001 5
b1001 6
b1001 3
b1101001 $
b1101001 #
b1101001 *
#1410
b0 0
b0 7
b1110000 !
b1110000 1
b111 ,
b111 <
b0 .
b0 5
b0 6
b0 3
b111 -
b111 :
b111 ;
b111 9
b1110000 $
b1110000 #
b1110000 *
#1430
b1110001 !
b1110001 1
b1 0
b1 7
b1 .
b1 5
b1 6
b1 3
b1110001 $
b1110001 #
b1110001 *
#1450
b1110010 !
b1110010 1
b10 0
b10 7
b10 .
b10 5
b10 6
b10 3
b1110010 $
b1110010 #
b1110010 *
#1470
b1110011 !
b1110011 1
b11 0
b11 7
b11 .
b11 5
b11 6
b11 3
b1110011 $
b1110011 #
b1110011 *
#1490
b1110100 !
b1110100 1
b100 0
b100 7
b100 .
b100 5
b100 6
b100 3
b1110100 $
b1110100 #
b1110100 *
#1510
b1110101 !
b1110101 1
b101 0
b101 7
b101 .
b101 5
b101 6
b101 3
b1110101 $
b1110101 #
b1110101 *
#1530
b1110110 !
b1110110 1
b110 0
b110 7
b110 .
b110 5
b110 6
b110 3
b1110110 $
b1110110 #
b1110110 *
#1550
b1110111 !
b1110111 1
b111 0
b111 7
b111 .
b111 5
b111 6
b111 3
b1110111 $
b1110111 #
b1110111 *
#1570
b1111000 !
b1111000 1
b1000 0
b1000 7
b1000 .
b1000 5
b1000 6
b1000 3
b1111000 $
b1111000 #
b1111000 *
#1590
b1111001 !
b1111001 1
b1001 0
b1001 7
b1001 .
b1001 5
b1001 6
b1001 3
b1111001 $
b1111001 #
b1111001 *
#1610
b0 0
b0 7
b10000000 !
b10000000 1
b1000 ,
b1000 <
b0 .
b0 5
b0 6
b0 3
b1000 -
b1000 :
b1000 ;
b1000 9
b10000000 $
b10000000 #
b10000000 *
#1630
b10000001 !
b10000001 1
b1 0
b1 7
b1 .
b1 5
b1 6
b1 3
b10000001 $
b10000001 #
b10000001 *
#1650
b10000010 !
b10000010 1
b10 0
b10 7
b10 .
b10 5
b10 6
b10 3
b10000010 $
b10000010 #
b10000010 *
#1670
b10000011 !
b10000011 1
b11 0
b11 7
b11 .
b11 5
b11 6
b11 3
b10000011 $
b10000011 #
b10000011 *
#1690
b10000100 !
b10000100 1
b100 0
b100 7
b100 .
b100 5
b100 6
b100 3
b10000100 $
b10000100 #
b10000100 *
#1710
b10000101 !
b10000101 1
b101 0
b101 7
b101 .
b101 5
b101 6
b101 3
b10000101 $
b10000101 #
b10000101 *
#1730
b10000110 !
b10000110 1
b110 0
b110 7
b110 .
b110 5
b110 6
b110 3
b10000110 $
b10000110 #
b10000110 *
#1750
b10000111 !
b10000111 1
b111 0
b111 7
b111 .
b111 5
b111 6
b111 3
b10000111 $
b10000111 #
b10000111 *
#1770
b10001000 !
b10001000 1
b1000 0
b1000 7
b1000 .
b1000 5
b1000 6
b1000 3
b10001000 $
b10001000 #
b10001000 *
#1790
b10001001 !
b10001001 1
b1001 0
b1001 7
b1001 .
b1001 5
b1001 6
b1001 3
b10001001 $
b10001001 #
b10001001 *
#1810
b0 0
b0 7
b10010000 !
b10010000 1
b1001 ,
b1001 <
b0 .
b0 5
b0 6
b0 3
b1001 -
b1001 :
b1001 ;
b1001 9
b10010000 $
b10010000 #
b10010000 *
#1830
b10010001 !
b10010001 1
b1 0
b1 7
b1 .
b1 5
b1 6
b1 3
b10010001 $
b10010001 #
b10010001 *
#1850
b10010010 !
b10010010 1
b10 0
b10 7
b10 .
b10 5
b10 6
b10 3
b10010010 $
b10010010 #
b10010010 *
#1870
b10010011 !
b10010011 1
b11 0
b11 7
b11 .
b11 5
b11 6
b11 3
b10010011 $
b10010011 #
b10010011 *
#1890
b10010100 !
b10010100 1
b100 0
b100 7
b100 .
b100 5
b100 6
b100 3
b10010100 $
b10010100 #
b10010100 *
#1910
b10010101 !
b10010101 1
b101 0
b101 7
b101 .
b101 5
b101 6
b101 3
b10010101 $
b10010101 #
b10010101 *
#1930
b10010110 !
b10010110 1
b110 0
b110 7
b110 .
b110 5
b110 6
b110 3
b10010110 $
b10010110 #
b10010110 *
#1950
b10010111 !
b10010111 1
b111 0
b111 7
b111 .
b111 5
b111 6
b111 3
b10010111 $
b10010111 #
b10010111 *
#1970
b10011000 !
b10011000 1
b1000 0
b1000 7
b1000 .
b1000 5
b1000 6
b1000 3
b10011000 $
b10011000 #
b10011000 *
#1990
b10011001 !
b10011001 1
b1001 0
b1001 7
b1001 .
b1001 5
b1001 6
b1001 3
b10011001 $
b10011001 #
b10011001 *
#2010
b0 ,
b0 <
b1 !
b1 1
b1 0
b1 7
b0 3
b0 -
b0 :
b0 ;
b0 9
b1 .
b1 5
b1 6
b1 2
b1 $
b0 #
b0 *
b1 "
b1 )
#2030
b10 !
b10 1
b10 0
b10 7
b10 .
b10 5
b10 6
b1 3
b10 $
b1 #
b1 *
#2050
b11 !
b11 1
b11 0
b11 7
b11 .
b11 5
b11 6
b10 3
b11 $
b10 #
b10 *
#2070
b100 !
b100 1
b100 0
b100 7
b100 .
b100 5
b100 6
b11 3
b100 $
b11 #
b11 *
#2090
b101 !
b101 1
b101 0
b101 7
b101 .
b101 5
b101 6
b100 3
b101 $
b100 #
b100 *
#2110
b110 !
b110 1
b110 0
b110 7
b110 .
b110 5
b110 6
b101 3
b110 $
b101 #
b101 *
#2130
b111 !
b111 1
b111 0
b111 7
b111 .
b111 5
b111 6
b110 3
b111 $
b110 #
b110 *
#2150
b1000 !
b1000 1
b1000 0
b1000 7
b1000 .
b1000 5
b1000 6
b111 3
b1000 $
b111 #
b111 *
#2170
b1001 !
b1001 1
b1001 0
b1001 7
b1001 .
b1001 5
b1001 6
b1000 3
b1001 $
b1000 #
b1000 *
#2190
b1 ,
b1 <
b1 -
b1 :
b1 ;
1/
b10000 !
b10000 1
b0 0
b0 7
b1010 .
b1010 5
b1010 6
b1001 3
b10000 $
b1001 #
b1001 *
#2210
0/
b1 0
b1 7
b10001 !
b10001 1
b1 ,
b1 <
b1 .
b1 5
b1 6
b0 3
b1 -
b1 :
b1 ;
b1 9
b10001 $
b10000 #
b10000 *
#2230
b10010 !
b10010 1
b10 0
b10 7
b10 .
b10 5
b10 6
b1 3
b10010 $
b10001 #
b10001 *
#2250
b10011 !
b10011 1
b11 0
b11 7
b11 .
b11 5
b11 6
b10 3
b10011 $
b10010 #
b10010 *
#2270
b10100 !
b10100 1
b100 0
b100 7
b100 .
b100 5
b100 6
b11 3
b10100 $
b10011 #
b10011 *
#2290
b10101 !
b10101 1
b101 0
b101 7
b101 .
b101 5
b101 6
b100 3
b10101 $
b10100 #
b10100 *
#2310
b10110 !
b10110 1
b110 0
b110 7
b110 .
b110 5
b110 6
b101 3
b10110 $
b10101 #
b10101 *
#2330
b10111 !
b10111 1
b111 0
b111 7
b111 .
b111 5
b111 6
b110 3
b10111 $
b10110 #
b10110 *
#2350
b11000 !
b11000 1
b1000 0
b1000 7
b1000 .
b1000 5
b1000 6
b111 3
b11000 $
b10111 #
b10111 *
#2370
b11001 !
b11001 1
b1001 0
b1001 7
b1001 .
b1001 5
b1001 6
b1000 3
b11001 $
b11000 #
b11000 *
#2390
b10 ,
b10 <
b10 -
b10 :
b10 ;
1/
b100000 !
b100000 1
b0 0
b0 7
b1010 .
b1010 5
b1010 6
b1001 3
b100000 $
b11001 #
b11001 *
#2410
0/
b1 0
b1 7
b100001 !
b100001 1
b10 ,
b10 <
b1 .
b1 5
b1 6
b0 3
b10 -
b10 :
b10 ;
b10 9
b100001 $
b100000 #
b100000 *
#2430
b100010 !
b100010 1
b10 0
b10 7
b10 .
b10 5
b10 6
b1 3
b100010 $
b100001 #
b100001 *
#2450
b100011 !
b100011 1
b11 0
b11 7
b11 .
b11 5
b11 6
b10 3
b100011 $
b100010 #
b100010 *
#2470
b100100 !
b100100 1
b100 0
b100 7
b100 .
b100 5
b100 6
b11 3
b100100 $
b100011 #
b100011 *
#2490
b100101 !
b100101 1
b101 0
b101 7
b101 .
b101 5
b101 6
b100 3
b100101 $
b100100 #
b100100 *
#2510
b100110 !
b100110 1
b110 0
b110 7
b110 .
b110 5
b110 6
b101 3
b100110 $
b100101 #
b100101 *
#2530
b100111 !
b100111 1
b111 0
b111 7
b111 .
b111 5
b111 6
b110 3
b100111 $
b100110 #
b100110 *
#2550
b101000 !
b101000 1
b1000 0
b1000 7
b1000 .
b1000 5
b1000 6
b111 3
b101000 $
b100111 #
b100111 *
#2570
b101001 !
b101001 1
b1001 0
b1001 7
b1001 .
b1001 5
b1001 6
b1000 3
b101001 $
b101000 #
b101000 *
#2590
b11 ,
b11 <
b11 -
b11 :
b11 ;
1/
b110000 !
b110000 1
b0 0
b0 7
b1010 .
b1010 5
b1010 6
b1001 3
b110000 $
b101001 #
b101001 *
#2610
0/
b1 0
b1 7
b110001 !
b110001 1
b11 ,
b11 <
b1 .
b1 5
b1 6
b0 3
b11 -
b11 :
b11 ;
b11 9
b110001 $
b110000 #
b110000 *
#2630
b110010 !
b110010 1
b10 0
b10 7
b10 .
b10 5
b10 6
b1 3
b110010 $
b110001 #
b110001 *
#2650
b110011 !
b110011 1
b11 0
b11 7
b11 .
b11 5
b11 6
b10 3
b110011 $
b110010 #
b110010 *
#2670
b110100 !
b110100 1
b100 0
b100 7
b100 .
b100 5
b100 6
b11 3
b110100 $
b110011 #
b110011 *
#2690
b110101 !
b110101 1
b101 0
b101 7
b101 .
b101 5
b101 6
b100 3
b110101 $
b110100 #
b110100 *
#2710
b110110 !
b110110 1
b110 0
b110 7
b110 .
b110 5
b110 6
b101 3
b110110 $
b110101 #
b110101 *
#2730
b110111 !
b110111 1
b111 0
b111 7
b111 .
b111 5
b111 6
b110 3
b110111 $
b110110 #
b110110 *
#2750
b111000 !
b111000 1
b1000 0
b1000 7
b1000 .
b1000 5
b1000 6
b111 3
b111000 $
b110111 #
b110111 *
#2770
b111001 !
b111001 1
b1001 0
b1001 7
b1001 .
b1001 5
b1001 6
b1000 3
b111001 $
b111000 #
b111000 *
#2790
b100 ,
b100 <
b100 -
b100 :
b100 ;
1/
b1000000 !
b1000000 1
b0 0
b0 7
b1010 .
b1010 5
b1010 6
b1001 3
b1000000 $
b111001 #
b111001 *
#2810
0/
b1 0
b1 7
b1000001 !
b1000001 1
b100 ,
b100 <
b1 .
b1 5
b1 6
b0 3
b100 -
b100 :
b100 ;
b100 9
b1000001 $
b1000000 #
b1000000 *
#2830
b1000010 !
b1000010 1
b10 0
b10 7
b10 .
b10 5
b10 6
b1 3
b1000010 $
b1000001 #
b1000001 *
#2850
b1000011 !
b1000011 1
b11 0
b11 7
b11 .
b11 5
b11 6
b10 3
b1000011 $
b1000010 #
b1000010 *
#2870
b1000100 !
b1000100 1
b100 0
b100 7
b100 .
b100 5
b100 6
b11 3
b1000100 $
b1000011 #
b1000011 *
#2890
b1000101 !
b1000101 1
b101 0
b101 7
b101 .
b101 5
b101 6
b100 3
b1000101 $
b1000100 #
b1000100 *
#2910
b1000110 !
b1000110 1
b110 0
b110 7
b110 .
b110 5
b110 6
b101 3
b1000110 $
b1000101 #
b1000101 *
#2930
b1000111 !
b1000111 1
b111 0
b111 7
b111 .
b111 5
b111 6
b110 3
b1000111 $
b1000110 #
b1000110 *
#2950
b1001000 !
b1001000 1
b1000 0
b1000 7
b1000 .
b1000 5
b1000 6
b111 3
b1001000 $
b1000111 #
b1000111 *
#2970
b1001001 !
b1001001 1
b1001 0
b1001 7
b1001 .
b1001 5
b1001 6
b1000 3
b1001001 $
b1001000 #
b1001000 *
#2990
b101 ,
b101 <
b101 -
b101 :
b101 ;
1/
b1010000 !
b1010000 1
b0 0
b0 7
b1010 .
b1010 5
b1010 6
b1001 3
b1010000 $
b1001001 #
b1001001 *
#3010
0/
b1 0
b1 7
b1010001 !
b1010001 1
b101 ,
b101 <
b1 .
b1 5
b1 6
b0 3
b101 -
b101 :
b101 ;
b101 9
b1010001 $
b1010000 #
b1010000 *
#3030
b1010010 !
b1010010 1
b10 0
b10 7
b10 .
b10 5
b10 6
b1 3
b1010010 $
b1010001 #
b1010001 *
#3050
b1010011 !
b1010011 1
b11 0
b11 7
b11 .
b11 5
b11 6
b10 3
b1010011 $
b1010010 #
b1010010 *
#3070
b1010100 !
b1010100 1
b100 0
b100 7
b100 .
b100 5
b100 6
b11 3
b1010100 $
b1010011 #
b1010011 *
#3090
b1010101 !
b1010101 1
b101 0
b101 7
b101 .
b101 5
b101 6
b100 3
b1010101 $
b1010100 #
b1010100 *
#3110
b1010110 !
b1010110 1
b110 0
b110 7
b110 .
b110 5
b110 6
b101 3
b1010110 $
b1010101 #
b1010101 *
#3130
b1010111 !
b1010111 1
b111 0
b111 7
b111 .
b111 5
b111 6
b110 3
b1010111 $
b1010110 #
b1010110 *
#3150
b1011000 !
b1011000 1
b1000 0
b1000 7
b1000 .
b1000 5
b1000 6
b111 3
b1011000 $
b1010111 #
b1010111 *
#3170
b1011001 !
b1011001 1
b1001 0
b1001 7
b1001 .
b1001 5
b1001 6
b1000 3
b1011001 $
b1011000 #
b1011000 *
#3190
b110 ,
b110 <
b110 -
b110 :
b110 ;
1/
b1100000 !
b1100000 1
b0 0
b0 7
b1010 .
b1010 5
b1010 6
b1001 3
b1100000 $
b1011001 #
b1011001 *
#3210
0/
b1 0
b1 7
b1100001 !
b1100001 1
b110 ,
b110 <
b1 .
b1 5
b1 6
b0 3
b110 -
b110 :
b110 ;
b110 9
b1100001 $
b1100000 #
b1100000 *
#3230
b1100010 !
b1100010 1
b10 0
b10 7
b10 .
b10 5
b10 6
b1 3
b1100010 $
b1100001 #
b1100001 *
#3250
b1100011 !
b1100011 1
b11 0
b11 7
b11 .
b11 5
b11 6
b10 3
b1100011 $
b1100010 #
b1100010 *
#3270
b1100100 !
b1100100 1
b100 0
b100 7
b100 .
b100 5
b100 6
b11 3
b1100100 $
b1100011 #
b1100011 *
#3290
b1100101 !
b1100101 1
b101 0
b101 7
b101 .
b101 5
b101 6
b100 3
b1100101 $
b1100100 #
b1100100 *
#3310
b1100110 !
b1100110 1
b110 0
b110 7
b110 .
b110 5
b110 6
b101 3
b1100110 $
b1100101 #
b1100101 *
#3330
b1100111 !
b1100111 1
b111 0
b111 7
b111 .
b111 5
b111 6
b110 3
b1100111 $
b1100110 #
b1100110 *
#3350
b1101000 !
b1101000 1
b1000 0
b1000 7
b1000 .
b1000 5
b1000 6
b111 3
b1101000 $
b1100111 #
b1100111 *
#3370
b1101001 !
b1101001 1
b1001 0
b1001 7
b1001 .
b1001 5
b1001 6
b1000 3
b1101001 $
b1101000 #
b1101000 *
#3390
b111 ,
b111 <
b111 -
b111 :
b111 ;
1/
b1110000 !
b1110000 1
b0 0
b0 7
b1010 .
b1010 5
b1010 6
b1001 3
b1110000 $
b1101001 #
b1101001 *
#3410
0/
b1 0
b1 7
b1110001 !
b1110001 1
b111 ,
b111 <
b1 .
b1 5
b1 6
b0 3
b111 -
b111 :
b111 ;
b111 9
b1110001 $
b1110000 #
b1110000 *
#3430
b1110010 !
b1110010 1
b10 0
b10 7
b10 .
b10 5
b10 6
b1 3
b1110010 $
b1110001 #
b1110001 *
#3450
b1110011 !
b1110011 1
b11 0
b11 7
b11 .
b11 5
b11 6
b10 3
b1110011 $
b1110010 #
b1110010 *
#3470
b1110100 !
b1110100 1
b100 0
b100 7
b100 .
b100 5
b100 6
b11 3
b1110100 $
b1110011 #
b1110011 *
#3490
b1110101 !
b1110101 1
b101 0
b101 7
b101 .
b101 5
b101 6
b100 3
b1110101 $
b1110100 #
b1110100 *
#3510
b1110110 !
b1110110 1
b110 0
b110 7
b110 .
b110 5
b110 6
b101 3
b1110110 $
b1110101 #
b1110101 *
#3530
b1110111 !
b1110111 1
b111 0
b111 7
b111 .
b111 5
b111 6
b110 3
b1110111 $
b1110110 #
b1110110 *
