Ch5/5.2/DiceGame/src/GameTest.v
module GameTest (
    input roll_i, win_i, lose_i,
    input clk, rst_n,
    output reg [4-1 : 0] sum_o,
    output reg Rb_o, Reset_o,
    output reg done
);
    // state
    localparam T0 = 0, T1 = 1, T2 = 2, T3 = 3;
    reg [2-1 : 0] Tstate, Tnext;

    parameter N = 12; // #(simulated dice rolls)

    always @(posedge clk, negedge rst_n) begin
        Tstate <= (!rst_n)? 0 : Tnext;
    end

    always @* begin
        Tnext = T0;

        case (Tstate)
            T0: begin
                if (i >= N) Tnext = T3;
                else if (roll_i) Tnext = T1;
                else Tnext = T0;
            end
            T1: Tnext = T2;
            T2: Tnext = T0;
        endcase
    end

    // Rb_o
    always @* begin
        Rb_o = 0;

        case (Tstate)
            T0: Rb_o = 1;
        endcase
    end

    // Reset_o
    always @* begin
        Reset_o = 0;

        case (Tstate)
            T2: if (win_i || lose_i) Reset_o = 1;
        endcase
    end

    // done
    always @* begin
        done = 0;

        case (Tstate)
            T3: done = 1;
        endcase
    end

    // sumarray
    reg [4-1 : 0] sumarray [0 : 12-1];

    always @(negedge rst_n) begin
        sumarray[0] = 7;
        sumarray[1] = 11;
        sumarray[2] = 2;
        sumarray[3] = 4;
        sumarray[4] = 7;
        sumarray[5] = 5;
        sumarray[6] = 6;
        sumarray[7] = 7;
        sumarray[8] = 6;
        sumarray[9] = 8;
        sumarray[10] = 9;
        sumarray[11] = 6;
    end

    // sum_o, i
    reg [4-1 : 0] i;

    always @(posedge clk, negedge rst_n) begin
        if (!rst_n) begin
            sum_o <= 0;
            i <= 0;
        end else begin
            case (Tstate)
                T0: begin
                    if (i < N && roll_i) begin
                        sum_o <= sumarray[i];
                        i <= i + 1;
                    end
                end
            endcase
        end
    end

    // Trig1
    reg Trig1;

    always @(posedge clk, negedge rst_n) begin
        if (!rst_n) Trig1 <= 0;
        else begin
            case (Tstate)
                T2: Trig1 <= ~Trig1;
            endcase
        end
    end
endmodule

Ch5/5.2/DiceGame/src/DiceGame.v
module DiceGame (
    input [4-1 : 0] sum_i,
    input Rb_i, Reset_i,
    input clk, rst_n,
    output reg roll_o, win_o, lose_o
);
    // test logic
    reg D7, D711, D2312;

    always @* begin
        D7 = 0;
        D711 = 0;
        D2312 = 0;

        if (sum_i == 7) D7 = 1;
        if ((sum_i == 7) || (sum_i == 11)) D711 = 1;
        if ((sum_i == 2) | (sum_i == 3) | (sum_i == 12)) D2312 = 1;
    end

    // point
    reg [4-1 : 0] point;
    reg Sp;

    always @(posedge clk, negedge rst_n) begin
        if (!rst_n) point <= 2;
        else if (Sp) point <= sum_i;
    end

    // win_o
    always @* begin
        win_o = 0;

        case (state)
            S2: win_o = 1;
        endcase
    end

    // lose_o
    always @* begin
        lose_o = 0;

        case (state)
            S3: lose_o = 1;
        endcase
    end

    // controller
    localparam S0 = 0, S1 = 1, S2 = 2, S3 = 3, S4 = 4, S5 = 5;
    reg [3-1 : 0] state, next_state;

    always @(posedge clk, negedge rst_n) begin
        state <= (!rst_n)? 0 : next_state;
    end

    always @* begin
        case (state)
            S0: next_state = (Rb_i)? S1 : S0;
            S1: begin
                if (Rb_i) next_state = S1;
                else if (D711) next_state = S2;
                else if (D2312) next_state = S3;
                else next_state = S4;
            end
            S2: next_state = (Reset_i)? S0 : S2;
            S3: next_state = (Reset_i)? S0 : S3;
            S4: next_state = (Rb_i)? S5: S4;
            S5: begin
                if (Rb_i) next_state = S5;
                else if (sum_i == point) next_state = S2;
                else if (D7) next_state = S3;
                else next_state = S4;
            end
        endcase
    end

    // Sp
    always @* begin
        Sp = 0;

        case (state)
            S1: if (!Rb_i && !D711 && !D2312) Sp = 1;
        endcase
    end

    // roll_o
    always @* begin
        roll_o = 0;

        case (state)
            S1, S5: if (Rb_i) roll_o = 1;
        endcase
    end
endmodule

Ch5/5.02/DiceGame/test/Tester.v
`timescale 1ns/1ns
module Tester;
    reg clk, rst_n;
    wire Rb, Reset;
    wire roll, win, lose;
    wire [4-1 : 0] sum;
    wire done;

    DiceGame uut1 (
        .sum_i(sum), .Rb_i(Rb), .Reset_i(Reset),
        .clk(clk), .rst_n(rst_n),
        .roll_o(roll), .win_o(win), .lose_o(lose)
    );

    GameTest uut2 (
        .roll_i(roll), .win_i(win), .lose_i(lose),
        .clk(clk), .rst_n(rst_n),
        .sum_o(sum), .Rb_o(Rb), .Reset_o(Reset),
        .done(done)
    );

    initial begin
        $dumpfile("DiceGame.vcd");
        $dumpvars;
    end

    initial begin
        clk = 0;
        forever #5 clk = ~clk;
    end

    initial begin
        force clk = 0;
        rst_n = 1;
        #2 rst_n = 0;
        #8 rst_n = 1;
        release clk;
    end

    always @* begin
        if (done) #10 $finish;
    end
endmodule

Ch5/5.2/DiceGame/test/DiceGame.vcd
$date
	Fri Nov  7 19:13:08 2025
$end
$version
	Icarus Verilog
$end
$timescale
	1ns
$end
$scope module Tester $end
$var wire 1 ! win $end
$var wire 4 " sum [3:0] $end
$var wire 1 # roll $end
$var wire 1 $ lose $end
$var wire 1 % done $end
$var wire 1 & Reset $end
$var wire 1 ' Rb $end
$var reg 1 ( clk $end
$var reg 1 ) rst_n $end
$scope module uut1 $end
$var wire 1 ( clk $end
$var wire 1 ) rst_n $end
$var wire 4 * sum_i [3:0] $end
$var wire 1 & Reset_i $end
$var wire 1 ' Rb_i $end
$var parameter 32 + S0 $end
$var parameter 32 , S1 $end
$var parameter 32 - S2 $end
$var parameter 32 . S3 $end
$var parameter 32 / S4 $end
$var parameter 32 0 S5 $end
$var reg 1 1 D2312 $end
$var reg 1 2 D7 $end
$var reg 1 3 D711 $end
$var reg 1 4 Sp $end
$var reg 1 $ lose_o $end
$var reg 3 5 next_state [2:0] $end
$var reg 4 6 point [3:0] $end
$var reg 1 # roll_o $end
$var reg 3 7 state [2:0] $end
$var reg 1 ! win_o $end
$upscope $end
$scope module uut2 $end
$var wire 1 ( clk $end
$var wire 1 $ lose_i $end
$var wire 1 # roll_i $end
$var wire 1 ) rst_n $end
$var wire 1 ! win_i $end
$var parameter 32 8 N $end
$var parameter 32 9 T0 $end
$var parameter 32 : T1 $end
$var parameter 32 ; T2 $end
$var parameter 32 < T3 $end
$var reg 1 ' Rb_o $end
$var reg 1 & Reset_o $end
$var reg 2 = Tnext [1:0] $end
$var reg 1 > Trig1 $end
$var reg 2 ? Tstate [1:0] $end
$var reg 1 % done $end
$var reg 4 @ i [3:0] $end
$var reg 4 A sum_o [3:0] $end
$upscope $end
$upscope $end
$enddefinitions $end
$comment Show the parameter values. $end
$dumpall
b11 <
b10 ;
b1 :
b0 9
b1100 8
b101 0
b100 /
b11 .
b10 -
b1 ,
b0 +
$end
#0
$dumpvars
bx A
bx @
bx ?
x>
bx =
bx 7
bx 6
bx 5
x4
x3
x2
x1
bx *
1)
0(
x'
x&
x%
x$
x#
bx "
x!
$end
#2
0#
04
0$
0!
0%
1'
0&
b0 =
b1 5
01
03
02
b10 6
b0 7
b0 ?
b0 @
b0 "
b0 *
b0 A
0>
0)
#5
0(
#10
b1 =
1#
b1 7
1(
1)
#15
0(
#20
0#
b10 5
0'
b10 =
13
12
b1 ?
b1 @
b111 "
b111 *
b111 A
1(
#25
0(
#30
b0 5
1&
b0 =
1!
b10 ?
b10 7
1(
#35
0(
#40
b1 5
0!
1'
0&
b0 7
b0 ?
1>
1(
#45
0(
#50
b1 =
1#
b1 7
1(
#55
0(
#60
0#
b10 5
0'
b10 =
13
02
b1 ?
b10 @
b1011 "
b1011 *
b1011 A
1(
#65
0(
#70
b0 5
1&
b0 =
1!
b10 ?
b10 7
1(
#75
0(
#80
b1 5
0!
1'
0&
b0 7
b0 ?
0>
1(
#85
0(
#90
b1 =
1#
b1 7
1(
#95
0(
#100
0#
b11 5
0'
b10 =
11
03
b1 ?
b11 @
b10 "
b10 *
b10 A
1(
#105
0(
#110
b0 5
1&
b0 =
1$
b10 ?
b11 7
1(
#115
0(
#120
b1 5
0$
1'
0&
b0 7
b0 ?
1>
1(
#125
0(
#130
b1 =
1#
b1 7
1(
#135
0(
#140
0#
b100 5
14
0'
b10 =
01
b1 ?
b100 @
b100 "
b100 *
b100 A
1(
#145
0(
#150
b0 =
04
b10 ?
b100 7
b100 6
1(
#155
0(
#160
b101 5
1'
b0 ?
0>
1(
#165
0(
#170
b1 =
1#
b101 7
1(
#175
0(
#180
0#
b11 5
0'
b10 =
13
12
b1 ?
b101 @
b111 "
b111 *
b111 A
1(
#185
0(
#190
b0 5
1&
b0 =
1$
b10 ?
b11 7
1(
#195
0(
#200
b1 5
0$
1'
0&
b0 7
b0 ?
1>
1(
#205
0(
#210
b1 =
1#
b1 7
1(
#215
0(
#220
0#
b100 5
14
0'
b10 =
03
02
b1 ?
b110 @
b101 "
b101 *
b101 A
1(
#225
0(
#230
b0 =
04
b10 ?
b100 7
b101 6
1(
#235
0(
#240
b101 5
1'
b0 ?
0>
1(
#245
0(
#250
b1 =
1#
b101 7
1(
#255
0(
#260
0#
b100 5
0'
b10 =
b1 ?
b111 @
b110 "
b110 *
b110 A
1(
#265
0(
#270
b0 =
b10 ?
b100 7
1(
#275
0(
#280
b101 5
1'
b0 ?
1>
1(
#285
0(
#290
b1 =
1#
b101 7
1(
#295
0(
#300
0#
b11 5
0'
b10 =
13
12
b1 ?
b1000 @
b111 "
b111 *
b111 A
1(
#305
0(
#310
b0 5
1&
b0 =
1$
b10 ?
b11 7
1(
#315
0(
#320
b1 5
0$
1'
0&
b0 7
b0 ?
0>
1(
#325
0(
#330
b1 =
1#
b1 7
1(
#335
0(
#340
0#
b100 5
14
0'
b10 =
03
02
b1 ?
b1001 @
b110 "
b110 *
b110 A
1(
#345
0(
#350
b0 =
04
b10 ?
b100 7
b110 6
1(
#355
0(
#360
b101 5
1'
b0 ?
1>
1(
#365
0(
#370
b1 =
1#
b101 7
1(
#375
0(
#380
0#
b100 5
0'
b10 =
b1 ?
b1010 @
b1000 "
b1000 *
b1000 A
1(
#385
0(
#390
b0 =
b10 ?
b100 7
1(
#395
0(
#400
b101 5
1'
b0 ?
0>
1(
#405
0(
#410
b1 =
1#
b101 7
1(
#415
0(
#420
0#
b100 5
0'
b10 =
b1 ?
b1011 @
b1001 "
b1001 *
b1001 A
1(
#425
0(
#430
b0 =
b10 ?
b100 7
1(
#435
0(
#440
b101 5
1'
b0 ?
1>
1(
#445
0(
#450
b1 =
1#
b101 7
1(
#455
0(
#460
0#
b10 5
0'
b10 =
b1 ?
b1100 @
b110 "
b110 *
b110 A
1(
#465
0(
#470
b0 5
1&
b0 =
1!
b10 ?
b10 7
1(
#475
0(
#480
b1 5
0!
1'
0&
b11 =
b0 7
b0 ?
0>
1(
#485
0(
#490
14
b100 5
0'
1%
b0 =
0#
b11 ?
b1 7
1(
#495
0(
#500
04
b101 5
0%
1'
b11 =
b100 7
b0 ?
1(
