NYCU/DigitalSystemsDesign/Ch4/03.32BitCLA/src/PartialFullAdder.v
module PartialFullAdder (
    input a, b,
    input cin,
    output s,
    output p, g
);
    assign s = a ^ b ^ cin; // sum

    assign p = a ^ b; // carry propogate
    assign g = a & b; // carry generate
endmodule

Ch4/03.32BitCLA/src/CLA4.v
module CLA4 (
    input [4-1 : 0] a, b,
    input c0, // carry in
    output [4-1 : 0] s, // sum
    output c4, // carry out
    output gg, pg // group propagate, group generate
);
    wire [3 : 1] c; // c3 ~ c1
    wire [4-1 : 0] p, g; // carry propagate, carry generate

    PartialFullAdder pfa_0 (
        .a(a[0]), .b(b[0]),
        .cin(c0),
        .s(s[0]),
        .p(p[0]), .g(g[0])
    );

    PartialFullAdder pfa_1 (
        .a(a[1]), .b(b[1]),
        .cin(c[1]),
        .s(s[1]),
        .p(p[1]), .g(g[1])
    );

    PartialFullAdder pfa_2 (
        .a(a[2]), .b(b[2]),
        .cin(c[2]),
        .s(s[2]),
        .p(p[2]), .g(g[2])
    );

    PartialFullAdder pfa_3 (
        .a(a[3]), .b(b[3]),
        .cin(c[3]),
        .s(s[3]),
        .p(p[3]), .g(g[3])
    );

    // controller
    assign c[1] = g[0] | (p[0] & c0);
    assign c[2] = g[1] | (p[1] & c[1]);
    assign c[3] = g[2] | (p[2] & c[2]);
    assign c4 = g[3] | (p[3] & c[3]);

    assign gg = g[3] | (p[3] & g[2]) | (p[3] & p[2] & g[1]) | (p[3] & p[2] & p[1] & g[0]); // group generate
    assign pg = &p; // group propagate
endmodule

NYCU/DigitalSystemsDesign/Ch4/03.32BitCLA/src/CLA16.v
module CLA16 (
    input [16-1 : 0] a, b,
    input cin,
    output [16-1 : 0] s,
    output cout
);
    wire [4-1 : 0] gg, pg; // group propagate, group generate

    wire c4, c8, c12;

    CLA4 adder4_3 (
        .a(a[15:12]), .b(b[15:12]),
        .c0(c12),
        .s(s[15:12]),
        .c4(),
        .gg(gg[3]),
        .pg(pg[3])
    );

    CLA4 adder4_2 (
        .a(a[11:8]), .b(b[11:8]),
        .c0(c8),
        .s(s[11:8]),
        .c4(),
        .gg(gg[2]),
        .pg(pg[2])
    );

    CLA4 adder4_1 (
        .a(a[7:4]), .b(b[7:4]),
        .c0(c4),
        .s(s[7:4]),
        .c4(),
        .gg(gg[1]),
        .pg(pg[1])
    );

    CLA4 adder4_0 (
        .a(a[3:0]), .b(b[3:0]),
        .c0(cin),
        .s(s[3:0]),
        .c4(),
        .gg(gg[0]),
        .pg(pg[0])
    );
    
    // controller
    assign c4 = gg[0] | (pg[0] & cin);
    assign c8 = gg[1] | (pg[1] & gg[0]) | (pg[1] & pg[1] & pg[0] & cin);
    assign c12 = gg[2] | (pg[2] & gg[1]) | (pg[2] & pg[1] & gg[0]) | (pg[2] & pg[1] & pg[0] & cin);
    assign cout = gg[3] | (pg[3] & gg[2]) | (pg[3] & pg[2] & gg[1]) | (pg[3] & pg[2] & pg[1] & gg[0]) | (pg[3] & pg[2] & pg[1] & pg[0] & cin);
endmodule

NYCU/DigitalSystemsDesign/Ch4/03.32BitCLA/src/CLA32.v
module CLA32 (
    input [32-1 : 0] a, b,
    output [33-1 : 0] s
);
    wire carry;

    CLA16 lower (
        .a(a[15:0]), .b(b[15:0]),
        .cin(1'b0),
        .s(s[15:0]),
        .cout(carry)
    );
    
    CLA16 upper (
        .a(a[31:16]), .b(b[31:16]),
        .cin(carry),
        .s(s[31:16]),
        .cout(s[32])
    );
endmodule

NYCU/DigitalSystemsDesign/Ch4/03.32BitCLA/test/CLA32_test.v
module t_CLA32;
    reg [32-1 : 0] a, b;
    wire [33-1 : 0] s;

    CLA32 uut (
        .a(a), .b(b),
        .s(s)
    );

    reg [32-1 : 0] i, j;
    reg [33-1 : 0] golden;

    initial begin
        $dumpfile("CLA32.vcd");
        $dumpvars;
    end

    integer seed = 5;

    initial begin
        repeat (100) begin
            a = $urandom(seed)%(2**32-1);
            b = $urandom(seed)%(2**32-1);

            // $display("%d, %d", a, b);

            golden = a + b;

            #10
            if (s !== golden) begin
                $display("a=%d, b=%d, ans=%b, golden=%d", a, b, s, golden);
                #10 $finish;
            end
        end

        $display("All test cases passed!");
        #10 $finish;
    end
endmodule

NYCU/DigitalSystemsDesign/Ch4/03.32BitCLA/test/CLA32.vcd
$date
	Tue Oct 28 18:45:48 2025
$end
$version
	Icarus Verilog
$end
$timescale
	1s
$end
$scope module t_CLA32 $end
$var wire 33 ! s [32:0] $end
$var reg 32 " a [31:0] $end
$var reg 32 # b [31:0] $end
$var reg 33 $ golden [32:0] $end
$var integer 32 % seed [31:0] $end
$scope module uut $end
$var wire 32 & a [31:0] $end
$var wire 32 ' b [31:0] $end
$var wire 33 ( s [32:0] $end
$var wire 1 ) carry $end
$scope module lower $end
$var wire 16 * a [15:0] $end
$var wire 16 + b [15:0] $end
$var wire 1 , c12 $end
$var wire 1 - c4 $end
$var wire 1 . c8 $end
$var wire 1 / cin $end
$var wire 1 ) cout $end
$var wire 16 0 s [15:0] $end
$var wire 4 1 pg [3:0] $end
$var wire 4 2 gg [3:0] $end
$scope module adder4_0 $end
$var wire 4 3 a [3:0] $end
$var wire 4 4 b [3:0] $end
$var wire 1 / c0 $end
$var wire 1 5 c4 $end
$var wire 1 6 gg $end
$var wire 4 7 s [3:0] $end
$var wire 1 8 pg $end
$var wire 4 9 p [3:0] $end
$var wire 4 : g [3:0] $end
$var wire 3 ; c [3:1] $end
$scope module pfa_0 $end
$var wire 1 < a $end
$var wire 1 = b $end
$var wire 1 / cin $end
$var wire 1 > g $end
$var wire 1 ? p $end
$var wire 1 @ s $end
$upscope $end
$scope module pfa_1 $end
$var wire 1 A a $end
$var wire 1 B b $end
$var wire 1 C cin $end
$var wire 1 D g $end
$var wire 1 E p $end
$var wire 1 F s $end
$upscope $end
$scope module pfa_2 $end
$var wire 1 G a $end
$var wire 1 H b $end
$var wire 1 I cin $end
$var wire 1 J g $end
$var wire 1 K p $end
$var wire 1 L s $end
$upscope $end
$scope module pfa_3 $end
$var wire 1 M a $end
$var wire 1 N b $end
$var wire 1 O cin $end
$var wire 1 P g $end
$var wire 1 Q p $end
$var wire 1 R s $end
$upscope $end
$upscope $end
$scope module adder4_1 $end
$var wire 4 S a [3:0] $end
$var wire 4 T b [3:0] $end
$var wire 1 - c0 $end
$var wire 1 U c4 $end
$var wire 1 V gg $end
$var wire 4 W s [3:0] $end
$var wire 1 X pg $end
$var wire 4 Y p [3:0] $end
$var wire 4 Z g [3:0] $end
$var wire 3 [ c [3:1] $end
$scope module pfa_0 $end
$var wire 1 \ a $end
$var wire 1 ] b $end
$var wire 1 - cin $end
$var wire 1 ^ g $end
$var wire 1 _ p $end
$var wire 1 ` s $end
$upscope $end
$scope module pfa_1 $end
$var wire 1 a a $end
$var wire 1 b b $end
$var wire 1 c cin $end
$var wire 1 d g $end
$var wire 1 e p $end
$var wire 1 f s $end
$upscope $end
$scope module pfa_2 $end
$var wire 1 g a $end
$var wire 1 h b $end
$var wire 1 i cin $end
$var wire 1 j g $end
$var wire 1 k p $end
$var wire 1 l s $end
$upscope $end
$scope module pfa_3 $end
$var wire 1 m a $end
$var wire 1 n b $end
$var wire 1 o cin $end
$var wire 1 p g $end
$var wire 1 q p $end
$var wire 1 r s $end
$upscope $end
$upscope $end
$scope module adder4_2 $end
$var wire 4 s a [3:0] $end
$var wire 4 t b [3:0] $end
$var wire 1 . c0 $end
$var wire 1 u c4 $end
$var wire 1 v gg $end
$var wire 4 w s [3:0] $end
$var wire 1 x pg $end
$var wire 4 y p [3:0] $end
$var wire 4 z g [3:0] $end
$var wire 3 { c [3:1] $end
$scope module pfa_0 $end
$var wire 1 | a $end
$var wire 1 } b $end
$var wire 1 . cin $end
$var wire 1 ~ g $end
$var wire 1 !" p $end
$var wire 1 "" s $end
$upscope $end
$scope module pfa_1 $end
$var wire 1 #" a $end
$var wire 1 $" b $end
$var wire 1 %" cin $end
$var wire 1 &" g $end
$var wire 1 '" p $end
$var wire 1 (" s $end
$upscope $end
$scope module pfa_2 $end
$var wire 1 )" a $end
$var wire 1 *" b $end
$var wire 1 +" cin $end
$var wire 1 ," g $end
$var wire 1 -" p $end
$var wire 1 ." s $end
$upscope $end
$scope module pfa_3 $end
$var wire 1 /" a $end
$var wire 1 0" b $end
$var wire 1 1" cin $end
$var wire 1 2" g $end
$var wire 1 3" p $end
$var wire 1 4" s $end
$upscope $end
$upscope $end
$scope module adder4_3 $end
$var wire 4 5" a [3:0] $end
$var wire 4 6" b [3:0] $end
$var wire 1 , c0 $end
$var wire 1 7" c4 $end
$var wire 1 8" gg $end
$var wire 4 9" s [3:0] $end
$var wire 1 :" pg $end
$var wire 4 ;" p [3:0] $end
$var wire 4 <" g [3:0] $end
$var wire 3 =" c [3:1] $end
$scope module pfa_0 $end
$var wire 1 >" a $end
$var wire 1 ?" b $end
$var wire 1 , cin $end
$var wire 1 @" g $end
$var wire 1 A" p $end
$var wire 1 B" s $end
$upscope $end
$scope module pfa_1 $end
$var wire 1 C" a $end
$var wire 1 D" b $end
$var wire 1 E" cin $end
$var wire 1 F" g $end
$var wire 1 G" p $end
$var wire 1 H" s $end
$upscope $end
$scope module pfa_2 $end
$var wire 1 I" a $end
$var wire 1 J" b $end
$var wire 1 K" cin $end
$var wire 1 L" g $end
$var wire 1 M" p $end
$var wire 1 N" s $end
$upscope $end
$scope module pfa_3 $end
$var wire 1 O" a $end
$var wire 1 P" b $end
$var wire 1 Q" cin $end
$var wire 1 R" g $end
$var wire 1 S" p $end
$var wire 1 T" s $end
$upscope $end
$upscope $end
$upscope $end
$scope module upper $end
$var wire 16 U" a [15:0] $end
$var wire 16 V" b [15:0] $end
$var wire 1 W" c12 $end
$var wire 1 X" c4 $end
$var wire 1 Y" c8 $end
$var wire 1 ) cin $end
$var wire 1 Z" cout $end
$var wire 16 [" s [15:0] $end
$var wire 4 \" pg [3:0] $end
$var wire 4 ]" gg [3:0] $end
$scope module adder4_0 $end
$var wire 4 ^" a [3:0] $end
$var wire 4 _" b [3:0] $end
$var wire 1 ) c0 $end
$var wire 1 `" c4 $end
$var wire 1 a" gg $end
$var wire 4 b" s [3:0] $end
$var wire 1 c" pg $end
$var wire 4 d" p [3:0] $end
$var wire 4 e" g [3:0] $end
$var wire 3 f" c [3:1] $end
$scope module pfa_0 $end
$var wire 1 g" a $end
$var wire 1 h" b $end
$var wire 1 ) cin $end
$var wire 1 i" g $end
$var wire 1 j" p $end
$var wire 1 k" s $end
$upscope $end
$scope module pfa_1 $end
$var wire 1 l" a $end
$var wire 1 m" b $end
$var wire 1 n" cin $end
$var wire 1 o" g $end
$var wire 1 p" p $end
$var wire 1 q" s $end
$upscope $end
$scope module pfa_2 $end
$var wire 1 r" a $end
$var wire 1 s" b $end
$var wire 1 t" cin $end
$var wire 1 u" g $end
$var wire 1 v" p $end
$var wire 1 w" s $end
$upscope $end
$scope module pfa_3 $end
$var wire 1 x" a $end
$var wire 1 y" b $end
$var wire 1 z" cin $end
$var wire 1 {" g $end
$var wire 1 |" p $end
$var wire 1 }" s $end
$upscope $end
$upscope $end
$scope module adder4_1 $end
$var wire 4 ~" a [3:0] $end
$var wire 4 !# b [3:0] $end
$var wire 1 X" c0 $end
$var wire 1 "# c4 $end
$var wire 1 ## gg $end
$var wire 4 $# s [3:0] $end
$var wire 1 %# pg $end
$var wire 4 &# p [3:0] $end
$var wire 4 '# g [3:0] $end
$var wire 3 (# c [3:1] $end
$scope module pfa_0 $end
$var wire 1 )# a $end
$var wire 1 *# b $end
$var wire 1 X" cin $end
$var wire 1 +# g $end
$var wire 1 ,# p $end
$var wire 1 -# s $end
$upscope $end
$scope module pfa_1 $end
$var wire 1 .# a $end
$var wire 1 /# b $end
$var wire 1 0# cin $end
$var wire 1 1# g $end
$var wire 1 2# p $end
$var wire 1 3# s $end
$upscope $end
$scope module pfa_2 $end
$var wire 1 4# a $end
$var wire 1 5# b $end
$var wire 1 6# cin $end
$var wire 1 7# g $end
$var wire 1 8# p $end
$var wire 1 9# s $end
$upscope $end
$scope module pfa_3 $end
$var wire 1 :# a $end
$var wire 1 ;# b $end
$var wire 1 <# cin $end
$var wire 1 =# g $end
$var wire 1 ># p $end
$var wire 1 ?# s $end
$upscope $end
$upscope $end
$scope module adder4_2 $end
$var wire 4 @# a [3:0] $end
$var wire 4 A# b [3:0] $end
$var wire 1 Y" c0 $end
$var wire 1 B# c4 $end
$var wire 1 C# gg $end
$var wire 4 D# s [3:0] $end
$var wire 1 E# pg $end
$var wire 4 F# p [3:0] $end
$var wire 4 G# g [3:0] $end
$var wire 3 H# c [3:1] $end
$scope module pfa_0 $end
$var wire 1 I# a $end
$var wire 1 J# b $end
$var wire 1 Y" cin $end
$var wire 1 K# g $end
$var wire 1 L# p $end
$var wire 1 M# s $end
$upscope $end
$scope module pfa_1 $end
$var wire 1 N# a $end
$var wire 1 O# b $end
$var wire 1 P# cin $end
$var wire 1 Q# g $end
$var wire 1 R# p $end
$var wire 1 S# s $end
$upscope $end
$scope module pfa_2 $end
$var wire 1 T# a $end
$var wire 1 U# b $end
$var wire 1 V# cin $end
$var wire 1 W# g $end
$var wire 1 X# p $end
$var wire 1 Y# s $end
$upscope $end
$scope module pfa_3 $end
$var wire 1 Z# a $end
$var wire 1 [# b $end
$var wire 1 \# cin $end
$var wire 1 ]# g $end
$var wire 1 ^# p $end
$var wire 1 _# s $end
$upscope $end
$upscope $end
$scope module adder4_3 $end
$var wire 4 `# a [3:0] $end
$var wire 4 a# b [3:0] $end
$var wire 1 W" c0 $end
$var wire 1 b# c4 $end
$var wire 1 c# gg $end
$var wire 4 d# s [3:0] $end
$var wire 1 e# pg $end
$var wire 4 f# p [3:0] $end
$var wire 4 g# g [3:0] $end
$var wire 3 h# c [3:1] $end
$scope module pfa_0 $end
$var wire 1 i# a $end
$var wire 1 j# b $end
$var wire 1 W" cin $end
$var wire 1 k# g $end
$var wire 1 l# p $end
$var wire 1 m# s $end
$upscope $end
$scope module pfa_1 $end
$var wire 1 n# a $end
$var wire 1 o# b $end
$var wire 1 p# cin $end
$var wire 1 q# g $end
$var wire 1 r# p $end
$var wire 1 s# s $end
$upscope $end
$scope module pfa_2 $end
$var wire 1 t# a $end
$var wire 1 u# b $end
$var wire 1 v# cin $end
$var wire 1 w# g $end
$var wire 1 x# p $end
$var wire 1 y# s $end
$upscope $end
$scope module pfa_3 $end
$var wire 1 z# a $end
$var wire 1 {# b $end
$var wire 1 |# cin $end
$var wire 1 }# g $end
$var wire 1 ~# p $end
$var wire 1 !$ s $end
$upscope $end
$upscope $end
$upscope $end
$upscope $end
$upscope $end
$enddefinitions $end
$comment Show the parameter values. $end
$dumpall
$end
#0
$dumpvars
1!$
1~#
0}#
0|#
1{#
0z#
0y#
0x#
0w#
0v#
0u#
0t#
0s#
0r#
0q#
0p#
0o#
0n#
0m#
0l#
0k#
0j#
0i#
b0 h#
b0 g#
b1000 f#
0e#
b1000 d#
0c#
0b#
b1000 a#
b0 `#
1_#
1^#
0]#
0\#
1[#
0Z#
1Y#
1X#
0W#
0V#
1U#
0T#
0S#
0R#
0Q#
0P#
0O#
0N#
1M#
1L#
0K#
1J#
0I#
b0 H#
b0 G#
b1101 F#
0E#
b1101 D#
0C#
0B#
b1101 A#
b0 @#
1?#
1>#
0=#
0<#
1;#
0:#
19#
08#
07#
16#
05#
04#
03#
12#
01#
10#
1/#
0.#
0-#
1,#
0+#
1*#
0)#
b11 (#
b0 '#
b1011 &#
0%#
b1100 $#
0##
0"#
b1011 !#
b0 ~"
0}"
1|"
0{"
1z"
1y"
0x"
0w"
1v"
0u"
1t"
0s"
1r"
0q"
1p"
0o"
1n"
1m"
0l"
0k"
0j"
1i"
1h"
1g"
b111 f"
b1 e"
b1110 d"
0c"
b0 b"
1a"
1`"
b1011 _"
b101 ^"
b1 ]"
b0 \"
b1000110111000000 ["
0Z"
0Y"
1X"
0W"
b1000110110111011 V"
b101 U"
1T"
0S"
0R"
1Q"
0P"
0O"
0N"
0M"
1L"
0K"
1J"
1I"
1H"
0G"
0F"
1E"
0D"
0C"
0B"
1A"
0@"
1?"
0>"
b101 ="
b100 <"
b1 ;"
0:"
b1010 9"
08"
07"
b101 6"
b100 5"
04"
13"
02"
11"
10"
0/"
1."
0-"
1,"
1+"
1*"
1)"
0("
0'"
1&"
0%"
1$"
1#"
1""
1!"
0~
1}
0|
b110 {
b110 z
b1001 y
0x
b101 w
1v
1u
b1111 t
b110 s
0r
0q
0p
0o
0n
0m
0l
0k
0j
0i
0h
0g
0f
0e
0d
0c
0b
0a
1`
1_
0^
1]
0\
b0 [
b0 Z
b1 Y
0X
b1 W
0V
0U
b1 T
b0 S
1R
1Q
0P
0O
1N
0M
0L
0K
0J
0I
0H
0G
1F
1E
0D
0C
1B
0A
1@
1?
0>
1=
0<
b0 ;
b0 :
b1011 9
08
b1011 7
06
05
b1011 4
b0 3
b100 2
b0 1
b1010010100011011 0
0/
0.
0-
1,
b101111100011011 +
b100011000000000 *
0)
b10001101110000001010010100011011 (
b10001101101110110101111100011011 '
b1010100011000000000 &
b10001101101110110101110010011011 %
b10001101110000001010010100011011 $
b10001101101110110101111100011011 #
b1010100011000000000 "
b10001101110000001010010100011011 !
$end
#10
1\#
0Y#
1V#
1P#
1%"
1Z"
b111 H#
1m#
0M#
0""
1W"
1Y"
1.
0t"
1u
0v
1b#
1c#
1"#
1##
0T"
04"
1f
1l
b10 2
1V
1s#
b11 d#
0!$
b1111 ]"
1C#
0?#
1q"
0z"
0Q"
1+"
11"
1c
1i
1p#
1|#
1<#
0n"
b1 ="
b111 {
b11 [
1U
b101 h#
1B#
b111 (#
b0 f"
b110 9"
1N"
0("
b0 w
0."
b110 W
0`
b110000001101111 0
b1111 7
1L
0S#
b1000 D#
1_#
b101 $#
1-#
0w"
b100111000010100100110000001101111 !
b100111000010100100110000001101111 (
b11100001010010 ["
b10 b"
0}"
b101 ;"
1M"
b0 <"
0L"
1x
1'"
0&"
b1111 y
1-"
b0 z
0,"
b0 Y
0_
1^
1d
b1011 Z
1p
b101 1
18
b1111 9
1K
1k#
b101 g#
1w#
1R#
b111 F#
0^#
b1000 G#
1]#
b1010 &#
0,#
1+#
b101 '#
17#
0i"
0v"
b10 d"
0|"
b1000 e"
1{"
00"
1b
1n
0B
0N
1j#
1u#
0J#
0U#
15#
0h"
0I"
0#"
0)"
1/"
1\
1a
1m
1A
1G
1M
1i#
1t#
1I#
1N#
1T#
1Z#
1)#
14#
0g"
0r"
1x"
b111 t
b1011 T
b1 4
b1101 a#
b1000 A#
b1111 !#
b1010 _"
b0 5"
b1000 s
b1011 S
b1110 3
b101 `#
b1111 @#
b101 ~"
b1000 ^"
b101011110110001 +
b1101100011111010 V"
b100010111110 *
b101111101011000 U"
b100111000010100100110000001101111 $
b11011000111110100101011110110001 #
b11011000111110100101011110110001 '
b1011111010110000000100010111110 "
b1011111010110000000100010111110 &
b11011000111110100101010010100001 %
#20
0P#
b110 H#
1k"
1M#
1)
0Y"
1-
0X"
15
16
0##
0,
01"
0R
1K"
1T"
b1011 2
18"
1l
1s#
1w"
b1100 ]"
0a"
b11 {
1c
1O
0"#
1Q"
0u
1i
1p#
00#
1t"
b100 ;
1B#
b111 ="
17"
b11 [
b101 h#
b110 (#
b10 f"
0`"
1."
0`
0@
b10 7
0L
0S#
b1 D#
0_#
1?#
0B"
0H"
b1100 9"
1N"
1""
1("
b111 w
04"
b1100011101000010 0
b100 W
0f
0m#
b1010 d#
1!$
1-#
b1101 $#
03#
b110100001110101011100011101000010 !
b110100001110101011100011101000010 (
b1010000111010101 ["
b101 b"
0q"
0-"
1_
0^
0?
08
b1010 9
0K
b100 :
1J
0R#
1Q#
b0 \"
0E#
b1101 F#
1^#
b10 G#
0]#
0>#
0A"
1@"
1G"
b10 ;"
0M"
1L"
b1101 <"
1R"
0!"
1~
0'"
b11 z
1&"
b0 1
0x
b0 y
03"
b11 Y
1e
b1000 Z
0d
1l#
0k#
b1 f#
0~#
b1100 g#
1}#
1,#
0+#
b1 &#
02#
b110 '#
11#
b0 d"
0p"
1o"
b10 e"
0{"
1P"
0*"
0]
0=
1H
1N
1O#
1U#
0[#
0;#
0y"
1>"
1C"
1I"
1O"
1|
1#"
0/"
0a
0M
0i#
1z#
0T#
0)#
1.#
1l"
0x"
b1101 6"
b11 t
b1010 T
b1100 4
b110 A#
b111 !#
b10 _"
b1111 5"
b11 s
b1001 S
b110 3
b1100 `#
b1011 @#
b110 ~"
b10 ^"
b1101001110101100 +
b1101011001110010 V"
b1111001110010110 *
b1100101101100010 U"
b110100001110101011100011101000010 $
b11010110011100101101001110101100 #
b11010110011100101101001110101100 '
b11001011011000101111001110010110 "
b11001011011000101111001110010110 &
b11010110011100101101000110010111 %
#30
0p#
0)
1Z"
1m#
0W"
1Y"
0N"
0i
0-
0K"
0\#
1X"
1f
0r
05
06
0y#
1##
0q"
0}"
b10 2
08"
1H"
1("
0c
0o
1R
0v#
1c#
1Y#
0C#
0n"
0z"
b1011 ]"
1a"
1"#
0E"
0Q"
1%"
b0 [
0O
b100 h#
0V#
0B#
1<#
0t"
07"
b0 ="
b11 {
b0 ;
1b#
b0 H#
b110 (#
b0 f"
1`"
1T"
14"
1@
1-#
0?#
b1011 9"
1B"
b1110 w
0""
0`
b110 W
1l
b1011111001101001 0
b1001 7
0F
1s#
b11 d#
0!$
1M#
b101 D#
0_#
b1 $#
09#
1k"
b100110101000101011011111001101001 !
b100110101000101011011111001101001 (
b11010100010101 ["
b101 b"
1w"
1S"
0R"
13"
1?
0,#
1>#
b1011 ;"
1A"
0@"
b0 <"
0L"
b1001 y
1!"
b10 z
0~
0_
b110 Y
1k
b1001 9
0E
b0 :
0J
1r#
b1011 f#
1~#
b100 g#
0}#
0L#
b0 G#
0Q#
b100 F#
0^#
b1100 &#
18#
b10 '#
07#
1j"
0o"
b101 d"
1v"
b1000 e"
1{"
1D"
0J"
0P"
10"
1=
0H
0O#
0*#
1;#
0m"
1y"
0>"
0C"
0I"
0|
0\
1g
0A
0G
1n#
0z#
0I#
0N#
0Z#
04#
1g"
0l"
1r"
1x"
b11 6"
b1011 t
b1001 4
b100 A#
b1110 !#
b1000 _"
b1000 5"
b10 s
b1100 S
b0 3
b110 `#
b0 @#
b10 ~"
b1101 ^"
b11101110101001 +
b1101010011101000 V"
b1000001011000000 *
b110000000101101 U"
b100110101000101011011111001101001 $
b11010100111010000011101110101001 #
b11010100111010000011101110101001 '
b1100000001011011000001011000000 "
b1100000001011011000001011000000 &
b11010100111010000011100011111101 %
#40
1N"
1q"
1K"
1n"
0H"
0k"
1E"
1_#
1)
0%"
0Z"
1\#
0B"
1,
1""
0Y#
0.
1V#
1X"
17"
18"
0b#
0c#
b100 9"
0T"
0."
1v
b1100 2
0V
1!$
1P#
10#
b11 ]"
1a"
1z"
1Q"
0+"
11"
0|#
b111 H#
16#
1t"
b111 ="
b100 {
1u
0U
b0 h#
b111 (#
b111 f"
1`"
0f
1L
0m#
0S#
1w"
1("
b1011 w
14"
b1100 W
1r
b100101111001111 0
b1111 7
1F
b1110 d#
1y#
b1000 D#
0M#
0-#
03#
b100 $#
19#
b11101000010001100100101111001111 !
b11101000010001100100101111001111 (
b1110100001000110 ["
b110 b"
0}"
0e
b1 1
18
1K
0l#
1R#
0v"
1u"
b100 <"
1L"
1'"
0&"
1,"
b11 y
03"
b1100 z
12"
b1100 Y
1q
b0 Z
0p
b1111 9
1E
b0 \"
0e#
b1110 f#
1x#
b0 g#
0w#
b111 F#
1L#
1,#
12#
01#
b1011 &#
08#
b100 '#
17#
1o"
b1001 d"
1|"
b110 e"
0{"
0?"
0D"
1J"
1P"
0}
1*"
0b
1h
0=
1H
0j#
1o#
0{#
1O#
0;#
1m"
1s"
1>"
1C"
1I"
0O"
1|
0#"
1)"
1/"
0g
0m
1<
1A
0n#
0t#
1z#
1I#
1)#
0.#
14#
1:#
1l"
0x"
b1100 6"
b1110 t
b1100 T
b1100 4
b110 a#
b110 A#
b110 !#
b1110 _"
b111 5"
b1101 s
b0 S
b11 3
b1000 `#
b1 @#
b1101 ~"
b111 ^"
b1100111011001100 +
b110011001101110 V"
b111110100000011 *
b1000000111010111 U"
b11101000010001100100101111001111 $
b1100110011011101100111011001100 #
b1100110011011101100111011001100 '
b10000001110101110111110100000011 "
b10000001110101110111110100000011 &
b1100110011011101100110001010011 %
#50
0P#
0)
1%"
1Z"
1M#
0""
0Y"
1.
07"
08"
1b#
1c#
b1001 ]"
0##
1T"
0\#
0K"
b110 2
1V
0!$
0n"
0w"
0Q"
11"
b10 H#
0B#
1+"
1O
1|#
0"#
0t"
b1 ="
b111 {
1u
1U
b100 ;
b100 h#
b100 f"
1N"
0."
1`
1R
1Y#
1_#
b1110 9"
1H"
1("
b10 w
04"
1f
b111 W
0r
0@
b1110001001111010 0
b1010 7
0L
1m#
b11 d#
0y#
b1101 D#
0S#
13#
b1110 $#
1?#
0k"
b100111101111000101110001001111010 !
b100111101111000101110001001111010 (
b11110111100010 ["
b10 b"
1q"
1M"
b0 <"
0L"
1-"
0,"
1_
0Q
0X#
1^#
b1101 ;"
0G"
0'"
1&"
b1101 y
13"
b10 z
02"
1e
b111 Y
0q
b1000 Z
1p
0?
b0 1
08
b10 9
0K
b100 :
1J
1l#
b1011 f#
0x#
b100 g#
1w#
b1001 F#
0R#
b10 G#
1Q#
02#
b110 '#
11#
b1 &#
0>#
0j"
b1010 d"
1p"
b100 e"
0o"
0J"
0P"
1}
0*"
1]
0h
0N
0o#
1{#
0U#
1[#
1*#
0y"
0C"
1O"
0|
1#"
0/"
1a
1g
1m
0<
1G
1i#
1n#
1t#
0z#
1N#
0)#
1.#
0:#
0g"
0l"
1x"
b0 6"
b1011 t
b1001 T
b100 4
b1100 a#
b1010 A#
b111 !#
b110 _"
b1101 5"
b110 s
b1110 S
b110 3
b111 `#
b11 @#
b110 ~"
b1100 ^"
b101110010100 +
b1100101001110110 V"
b1101011011100110 *
b111001101101100 U"
b100111101111000101110001001111010 $
b11001010011101100000101110010100 #
b11001010011101100000101110010100 '
b1110011011011001101011011100110 "
b1110011011011001101011011100110 &
b11001010011101100000100100011001 %
#60
0H"
0E"
b0 ="
0%"
0Z"
1B"
0,
1""
0.
0X"
0u
14"
0b#
0c#
b0 ]"
0a"
1r
1y#
0v
01"
b0 2
0V
0R
1!$
b1001 D#
0Y#
19#
1o
1v#
0"#
0z"
0+"
0O
0|#
0V#
16#
0<#
0`"
b100 [
b0 f"
b0 {
0U
b0 ;
b10 h#
b0 H#
b11 (#
b1011 W
0l
b11 7
1@
b1101 d#
0s#
1?#
1w"
b1001 9"
0N"
1("
b1001101110110011 0
b1011 w
0."
0-#
b1100 $#
03#
b11011001110001101001101110110011 !
b11011001110001101001101110110011 (
b1101100111000110 ["
b110 b"
0}"
b11 Y
0k
1j
b11 9
1?
b1001 f#
0r#
1q#
1>#
1v"
b0 e"
0u"
b1001 ;"
0M"
1'"
b0 z
0&"
b1011 y
0-"
b100 Z
0p
b0 :
0J
b10 g#
0w#
b0 G#
0Q#
0,#
1+#
b1010 &#
12#
01#
b1 '#
07#
b110 d"
0|"
0]
1b
1h
0n
1=
1B
0H
1j#
1o#
0u#
1J#
0O#
0[#
05#
1;#
0s"
0I"
0#"
0)"
1\
0a
0m
0A
0G
0i#
0t#
0I#
0N#
1Z#
1)#
0.#
04#
0x"
b110 T
b11 4
b1011 a#
b1 A#
b1011 !#
b10 _"
b1001 5"
b0 s
b101 S
b0 3
b10 `#
b1000 @#
b1 ~"
b100 ^"
b101101100011 +
b1011000110110010 V"
b1001000001010000 *
b10100000010100 U"
b11011001110001101001101110110011 $
b10110001101100100000101101100011 #
b10110001101100100000101101100011 '
b101000000101001001000001010000 "
b101000000101001001000001010000 &
b10110001101100100000100011001111 %
#70
1n"
1)
1.
1Y"
18"
1."
b1010 2
1V
1|#
1<#
b10 ]"
1##
1+"
1i
1o
1U
1C
1p#
1v#
b111 (#
1t"
17"
b10 {
b110 [
b1 ;
b111 h#
1"#
b11 f"
1H"
1N"
b111 9"
0T"
1""
04"
1F
1!$
1M#
0k"
1}"
b101 w
0("
0f
0l
b1 W
0r
0@
1L
b111010100011110 0
b1110 7
1R
0m#
0s#
b1000 d#
0y#
1S#
b1111 D#
1Y#
09#
b1000 $#
1?#
1q"
b10001111100011100111010100011110 !
b10001111100011100111010100011110 (
b1000111110001110 ["
b1110 b"
1w"
1G"
1M"
b111 ;"
0S"
b1000 <"
1R"
0!"
03"
0E
0~#
0L#
1j"
1|"
b0 y
0'"
b10 z
1&"
0e
1d
0X
1k
b10 Z
0j
b1101 Y
1q
0?
b1 :
1>
b0 1
08
1K
b1100 9
1Q
0l#
1k#
0e#
1r#
b1 g#
0q#
b110 f#
1x#
b0 \"
0E#
1R#
b1110 F#
1X#
18#
b110 &#
0>#
b1001 '#
1=#
0p"
b10 e"
1o"
b1001 d"
0v"
1D"
1J"
1P"
0}
00"
0B
0{#
0J#
1h"
1y"
1#"
1a
0g
1m
1<
1G
1M
1i#
0n#
1t#
1N#
1T#
14#
1:#
1l"
0r"
b1110 6"
b10 t
b1 4
b11 a#
b0 A#
b1011 _"
b10 s
b1011 S
b1101 3
b101 `#
b1110 @#
b1101 ~"
b10 ^"
b1110001001100001 +
b11000010111011 V"
b1001001010111101 *
b101111011010010 U"
b10001111100011100111010100011110 $
b110000101110111110001001100001 #
b110000101110111110001001100001 '
b1011110110100101001001010111101 "
b1011110110100101001001010111101 &
b110000101110111110000011110101 %
