Ch4/08.ShiftAddMultiplier/src/Datapath.v
// 8-bit unsigned shift-add multiplier
module Datapath (
    input load_i, sh_i, ad_i,
    input [4-1 : 0] mplier_i, mcand_i,
    input clk, rst_n,
    output M_o,
    output [8-1 : 0] product_o
);
    // acc
    reg [9-1 : 0] acc;

    always @(posedge clk, negedge rst_n) begin
        if (!rst_n) acc <= 0;
        else begin
            if (load_i) acc <= {5'b0, mplier_i};
            if (sh_i) acc <= acc >> 1;
            if (ad_i) acc <= acc + {mcand_i, 4'b0};
        end
    end

    // M_o
    assign M_o = acc[0];

    // product_o
    assign product_o = acc[7:0];
endmodule

Ch5/5.2/BinaryMultiplierController/Counter.v
module Counter (
    input sh_i, load_i,
    input clk, rst_n, st,
    output reg K_o
);
    // Q: 0 ~ 3
    reg [2-1 : 0] Q;

    always @(posedge clk, negedge rst_n) begin
        if (!rst_n) Q <= 0;
        else if (load_i) Q <= 0;
        else if (sh_i) Q <= Q + 1;
    end

    // K_o
    always @* begin
        K_o = 0;

        if (Q == 3 && sh_i) K_o = 1;
    end
endmodule

Ch4/08.ShiftAddMultiplier/src/Controller.v
module Controller (
    input M_i,
    input clk, rst_n, st,
    output load_o, sh_o,
    output reg ad_o,
    output reg done
);
    localparam S0 = 0, S1 = 1, S2 = 2, S3 = 3;
    reg [2-1 : 0] state, next_state;

    // state
    always @(posedge clk, negedge rst_n) begin
        state <= (!rst_n)? S0 : next_state;
    end

    always @* begin
        case (state)
            S0: next_state = (st)? S1 : S0;
            S1: begin
                if (M_i) next_state = S2;
                else next_state = (K)? S3 : S1;
            end
            S2: next_state = (K)? S3 : S1;
            S3: next_state = S0;
        endcase
    end

    // load_o
    reg load;

    always @* begin
        load = 0;

        case (state)
            S0: if (st) load = 1;
        endcase
    end

    assign load_o = load;

    // sh, sh_o
    reg sh;

    always @* begin
        sh = 0;

        case (state)
            S1: if (!M_i) sh = 1;
            S2: sh = 1;
        endcase
    end

    assign sh_o = sh;

    // ad_o
    always @* begin
        ad_o = 0;

        case (state)
            S1: if (M_i) ad_o = 1;
        endcase
    end

    // done
    always @* begin
        done = 0;

        case (state)
            S3: done = 1;
        endcase
    end

    Counter u1 (
        .sh_i(sh), .load_i(load),
        .clk(clk), .st(st), .rst_n(rst_n),
        .K_o(K)
    );
endmodule

Ch4/08.ShiftAddMultiplier/src/ShiftAddMultiplier.v
module ShiftAddMultiplier (
    input [4-1 : 0] mcand_i, mplier_i,
    input clk, st, rst_n,
    output [8-1 : 0] product_o,
    output done
);
    wire K, M, load, sh, ad;

    Controller u1 (
        .M_i(M),
        .clk(clk), .st(st), .rst_n(rst_n),
        .load_o(load), .sh_o(sh), .ad_o(ad),
        .done(done)
    );

    Datapath u3 (
        .load_i(load), .sh_i(sh), .ad_i(ad), .mplier_i(mplier_i), .mcand_i(mcand_i),
        .clk(clk), .rst_n(rst_n),
        .M_o(M), .product_o(product_o)
    );
endmodule

Ch4/08.ShiftAddMultiplier/test/ShiftAddMultiplier_test.v
`timescale 1ns/1ps
module t_ShiftAddMultiplier;
    reg [4-1 : 0] mcand, mplier;
    reg clk, st, rst_n;
    wire [8-1 : 0] product;
    wire done;

    ShiftAddMultiplier uut (
        .mcand_i(mcand), .mplier_i(mplier),
        .clk(clk), .st(st), .rst_n(rst_n),
        .product_o(product),
        .done(done)
    );

    initial begin
        $dumpfile("ShiftAddMultiplier.vcd");
        $dumpvars;
    end

    initial begin
        clk = 0;
        forever #5 clk = ~clk;
    end

    initial begin
        st = 0;
        mcand = 7;
        mplier = 11;

        // reset the circuit
        rst_n = 1;
        force clk = 0;
        #2 rst_n = 0;
        #8 release clk;
        @(posedge clk);
        #2 rst_n = 1;

        // start calculating
        #2 st = 1;
        @(posedge clk);
        #2 st = 0;

        // wait for 10 cycles
        repeat(8) @(posedge clk);

        #10 $finish;
    end
endmodule

Ch4/08.ShiftAddMultiplier/test/ShiftAddMultiplier.vcd
$date
	Thu Nov  6 15:28:02 2025
$end
$version
	Icarus Verilog
$end
$timescale
	1ps
$end
$scope module t_ShiftAddMultiplier $end
$var wire 8 ! product [7:0] $end
$var wire 1 " done $end
$var reg 1 # clk $end
$var reg 4 $ mcand [3:0] $end
$var reg 4 % mplier [3:0] $end
$var reg 1 & rst_n $end
$var reg 1 ' st $end
$scope module uut $end
$var wire 1 # clk $end
$var wire 4 ( mcand_i [3:0] $end
$var wire 4 ) mplier_i [3:0] $end
$var wire 1 & rst_n $end
$var wire 1 ' st $end
$var wire 1 * sh $end
$var wire 8 + product_o [7:0] $end
$var wire 1 , load $end
$var wire 1 " done $end
$var wire 1 - ad $end
$var wire 1 . M $end
$scope module u1 $end
$var wire 1 # clk $end
$var wire 1 , load_o $end
$var wire 1 & rst_n $end
$var wire 1 * sh_o $end
$var wire 1 ' st $end
$var wire 1 . M_i $end
$var wire 1 / K $end
$var parameter 32 0 S0 $end
$var parameter 32 1 S1 $end
$var parameter 32 2 S2 $end
$var parameter 32 3 S3 $end
$var reg 1 - ad_o $end
$var reg 1 " done $end
$var reg 1 4 load $end
$var reg 2 5 next_state [1:0] $end
$var reg 1 6 sh $end
$var reg 2 7 state [1:0] $end
$scope module u1 $end
$var wire 1 # clk $end
$var wire 1 4 load_i $end
$var wire 1 & rst_n $end
$var wire 1 6 sh_i $end
$var wire 1 ' st $end
$var reg 1 / K_o $end
$var reg 2 8 Q [1:0] $end
$upscope $end
$upscope $end
$scope module u3 $end
$var wire 1 - ad_i $end
$var wire 1 # clk $end
$var wire 1 , load_i $end
$var wire 4 9 mcand_i [3:0] $end
$var wire 4 : mplier_i [3:0] $end
$var wire 1 & rst_n $end
$var wire 1 * sh_i $end
$var wire 8 ; product_o [7:0] $end
$var wire 1 . M_o $end
$var reg 9 < acc [8:0] $end
$upscope $end
$upscope $end
$upscope $end
$enddefinitions $end
$comment Show the parameter values. $end
$dumpall
b11 3
b10 2
b1 1
b0 0
$end
#0
$dumpvars
bx <
bx ;
b1011 :
b111 9
bx 8
bx 7
x6
bx 5
04
x/
x.
x-
0,
bx +
x*
b1011 )
b111 (
0'
1&
b1011 %
b111 $
0#
x"
bx !
$end
#2000
0/
0"
0-
0*
06
b0 5
0.
b0 !
b0 +
b0 ;
b0 8
b0 7
b0 <
0&
#5000
0#
#10000
1#
#12000
1&
#14000
b1 5
1,
14
1'
#15000
0#
#20000
1-
0,
04
b10 5
1.
b1011 !
b1011 +
b1011 ;
b1 7
b1011 <
1#
#22000
0'
#25000
0#
#30000
b1111011 !
b1111011 +
b1111011 ;
0-
1*
16
b1 5
b1111011 <
b10 7
1#
#35000
0#
#40000
0*
06
1-
b10 5
b111101 !
b111101 +
b111101 ;
b1 8
b1 7
b111101 <
1#
#45000
0#
#50000
b10101101 !
b10101101 +
b10101101 ;
0-
1*
16
b1 5
b10101101 <
b10 7
1#
#55000
0#
#60000
1*
16
0.
b1010110 !
b1010110 +
b1010110 ;
b10 8
b1 7
b1010110 <
1#
#65000
0#
#70000
1-
0*
06
b10 5
1.
b101011 !
b101011 +
b101011 ;
0/
b101011 <
b11 8
1#
#75000
0#
#80000
1/
1*
16
0-
b11 5
b10011011 !
b10011011 +
b10011011 ;
b10 7
b10011011 <
1#
#85000
0#
#90000
b1001101 !
b1001101 +
b1001101 ;
1"
0*
06
b0 5
0/
b1001101 <
b11 7
b0 8
1#
#95000
0#
#100000
0"
b0 7
1#
